Workbook
Name \0: #REF!
Name \0: #REF!
Name \0: #REF!
Name \A: '[1]FULL-BAL'!#REF!
Name \A: '[1]FULL-BAL'!#REF!
Name \A: '[1]FULL-BAL'!#REF!
Name \B: #REF!
Name \B: #REF!
Name \B: #REF!
Name \C: #REF!
Name \C: #REF!
Name \C: #REF!
Name \D: #REF!
Name \D: #REF!
Name \D: #REF!
Name \E: #REF!
Name \E: #REF!
Name \E: #REF!
Name \F: #REF!
Name \F: #REF!
Name \F: #REF!
Name \G: #REF!
Name \G: #REF!
Name \G: #REF!
Name \J: [2]Sheet1!$A$64
Name \L: [2]Sheet1!$B$16
Name \P: #REF!
Name \P: #REF!
Name \P: #REF!
Name \R: [2]Sheet1!$B$81
Name \T: [2]Sheet1!$B$86
Name \W: [2]Sheet1!$B$21
Name \X: [2]Sheet1!$A$69
Name \z: #REF!
Name \z: #REF!
Name \z: #REF!
Name ___________DAT1: #REF!
Name ___________DAT1: #REF!
Name ___________DAT1: #REF!
Name ___________DAT10: #REF!
Name ___________DAT10: #REF!
Name ___________DAT10: #REF!
Name ___________DAT11: #REF!
Name ___________DAT11: #REF!
Name ___________DAT11: #REF!
Name ___________DAT12: #REF!
Name ___________DAT12: #REF!
Name ___________DAT12: #REF!
Name ___________DAT13: #REF!
Name ___________DAT13: #REF!
Name ___________DAT13: #REF!
Name ___________DAT14: #REF!
Name ___________DAT14: #REF!
Name ___________DAT14: #REF!
Name ___________DAT17: #REF!
Name ___________DAT17: #REF!
Name ___________DAT17: #REF!
Name ___________DAT2: #REF!
Name ___________DAT2: #REF!
Name ___________DAT2: #REF!

Sheet SoFP
B1: ABC Savings and Credit Cooperative Limited
B2: Statement of Financial Position
B3: As on 32nd Ashadh, 2082
E4: Amount in NPR
E5: Restated | F5: Restated
B6: Particulars | C6: Note | D6: As at 32nd Ashadh 2082 | E6: As at 31st Ashadh 2081 | F6: As on 1st Shrawan 2080
B7: Assets
B8: Cash and Cash Equivalents | C8: 4.1 | D8: ='4.1-4.4'!D14 -> 7642628.6 | E8: ='4.1-4.4'!E14 -> 6871672.2 | F8: ='4.1-4.4'!F14 -> 6246974.7
B9: Placement with Bank and Financial Institutions | C9: 4.2 | D9: ='4.1-4.4'!D23 -> 10319988 | E9: ='4.1-4.4'!E23 -> 9375829.9 | F9: ='4.1-4.4'!F23 -> 9282999.9
B10: Loans and Advances to Members | C10: 4.3 | D10: ='4.1-4.4'!D53 -> 1.2713279e+08 | E10: ='4.1-4.4'!E53 -> 1.2535608e+08 | F10: ='4.1-4.4'!F53 -> 1.2327044e+08
B11: Loans and Advances to Staff | C11: 4.4 | D11: ='4.1-4.4'!D117 -> 5078018.6 | E11: ='4.1-4.4'!E117 -> 3980298.8 | F11: ='4.1-4.4'!F117 -> 3459135.8
B12: Investment Securities | C12: 4.5 | D12: ='4.5'!E10 -> 1211000 | E12: ='4.5'!H10 -> 951000 | F12: ='4.5'!K10 -> 951000
B13: Current Tax Assets | C13: 4.6 | D13: ='4.6-4.7'!D14 -> 716999.27 | E13: ='4.6-4.7'!E14 -> 842646.05 | F13: ='4.6-4.7'!F14 -> 706629.3
B14: Investment Property | C14: 4.7 | D14: ='4.6-4.7'!D26 -> 2134450 | E14: ='4.6-4.7'!E26 -> 1984450 | F14: ='4.6-4.7'!F26 -> 934450
B15: Property, Plant and Equipment | C15: 4.8 | D15: ='4.8'!I35 -> 23292263 | E15: ='4.8'!I34 -> 21316775 | F15: ='4.8'!I33 -> 20475463
B16: Goodwill and Intangible Assets | C16: 4.9 | D16: ='4.9'!E39 -> 902276.54 | E16: ='4.9'!E38 -> 775855.79 | F16: ='4.9'!E37 -> 693769.8
B17: Other Assets | C17: 4.11 | D17: ='4.11-4.17'!D16 -> 7322069.3 | E17: ='4.11-4.17'!E16 -> 3010457.2 | F17: ='4.11-4.17'!F16 -> 2838262.3
B18: Total Assets | D18: =SUM(D8:D17) -> 1.8575248e+08 | E18: =SUM(E8:E17) -> 1.7446507e+08 | F18: =SUM(F8:F17) -> 1.6885913e+08
B20: Particulars | C20: Note | D20: =D6 -> As at 32nd Ashadh 2082 | E20: =E6 -> As at 31st Ashadh 2081 | F20: =F6 -> As on 1st Shrawan 2080
B21: Liabilities
B22: Deposits from Member | C22: 4.12 | D22: ='4.11-4.17'!D35 -> 1.4127537e+08 | E22: ='4.11-4.17'!E35 -> 1.344776e+08 | F22: ='4.11-4.17'!F35 -> 1.2985105e+08
B23: Borrowings | C23: 4.13 | D23: ='4.11-4.17'!D43 -> 2305000 | E23: ='4.11-4.17'!E43 -> 1312500 | F23: ='4.11-4.17'!F43 -> 1565500
B24: Provision for Employee Benefits | C24: 4.14 | D24: ='4.11-4.17'!D55 -> 2942703.8 | E24: ='4.11-4.17'!E55 -> 2496203.4 | F24: ='4.11-4.17'!F55 -> 2113505.1
B25: Deferred Tax Liabilities | C25: 4.10 | D25: =-'4.10'!D16 -> 481295.89 | E25: =-'4.10'!E16 -> 364141.49 | F25: =-'4.10'!E12 -> 1064561.5
B26: Grant Liabilities | C26: 4.15 | D26: ='4.11-4.17'!D102 -> 534940.15 | E26: ='4.11-4.17'!E102 -> 629000 | F26: ='4.11-4.17'!F102 -> 977540.61
B27: Other Liabilities | C27: 4.16 | D27: ='4.11-4.17'!D137 -> 2308138.8 | E27: ='4.11-4.17'!E137 -> 2000579.2 | F27: ='4.11-4.17'!F137 -> 1981037
B28: Total Liabilities | D28: =SUM(D22:D27) -> 1.4984745e+08 | E28: =SUM(E22:E27) -> 1.4128002e+08 | F28: =SUM(F22:F27) -> 1.375532e+08
B29: Equity
B30: Share Capital | C30: 4.17 | D30: ='4.11-4.17'!D144 -> 17186000 | E30: ='4.11-4.17'!E144 -> 15686000 | F30: ='4.11-4.17'!F144 -> 13732000
B31: General Reserve Fund | C31: 4.18 | D31: =SoCE!D45 -> 9101245 | E31: ='4.18-4.21'!E13 -> 7953754.8 | F31: ='4.18-4.21'!F13 -> 7076728.8
B32: Patronage Refund Reserve | D32: =SoCE!F45 -> 198232.14 | E32: =SoCE!F25 -> 555781.05 | F32: =SoCE!F8 -> 570291.02
B33: Other Statutory Reserves | C33: 4.19 | D33: =SoCE!H45 -> 4891133.9 | E33: ='4.18-4.21'!E26 -> 7886297.1 | F33: ='4.18-4.21'!F26 -> 9391418.9
B34: Revaluation Reserve | D34: =SoCE!E45 -> 3828421.4 | E34: =SoCE!E25 -> 2730846.1 | F34: =SoCE!E8 -> 2730846.1
B35: Fair Value Reserve | D35: =SoCE!G45 -> 700000 | E35: =SoCE!G25 -> 550000 | F35: =SoCE!G8 -> 300000
B36: Retained Earnings | D36: =SoCE!I45 -> 0 | E36: =SoCE!I25 -> -2177633.3 | F36: =SoCE!I8 -> -2495355.1
B37: Total Equity | D37: =SUM(D30:D36) -> 35905032 | E37: =SUM(E30:E36) -> 33185046 | F37: =SUM(F30:F36) -> 31305930
B38: Total Liabilities and Equity | D38: =D37+D28 -> 1.8575248e+08 | E38: =E37+E28 -> 1.7446507e+08 | F38: =F37+F28 -> 1.6885913e+08
E39: As per our report of even date
B41: * Note: Under the SMEs framework, the three-column presentation is optional; however, reconciliation of equity is mandatory.
D49: =D38-D18 -> 0 | E49: =E38-E18 -> 0 | F49: =F38-F18 -> 0

Sheet SoPL
B1: =SoFP!B1 -> ABC Savings and Credit Cooperative Limited
B2: Statement of Profit or Loss
B3: For the year ended 32nd Ashadh, 2082
E5: =SoFP!E4 -> Amount in NPR
E6: Restated
B7: Particulars | C7: Note | D7: FY 2081/82 | E7: FY 2080/81
B8: Interest Income | C8: 4.22 | D8: ='4.22-4.33'!D12 -> 19029139 | E8: ='4.22-4.33'!E12 -> 15739642
B9: Interest Expense | C9: 4.23 | D9: =-'4.22-4.33'!D20 -> -7819121.1 | E9: =-'4.22-4.33'!E20 -> -6913198.5
B10: Net Interest Income | D10: =SUM(D8:D9) -> 11210018 | E10: =SUM(E8:E9) -> 8826443.6
B11: Sales and Other Operating Income | C11: 4.24 | D11: ='4.22-4.33'!D31 -> 2239352.8 | E11: ='4.22-4.33'!E31 -> 1666057.5
B12: Cost of Goods Sold and Other Direct Expenses | C12: 4.25 | D12: =-'4.22-4.33'!D61 -> -268855.73 | E12: =-'4.22-4.33'!E61 -> -222747.24
B13: Net Sales and Other Operating Income | D13: =SUM(D11:D12) -> 1970497 | E13: =SUM(E11:E12) -> 1443310.3
B14: Net Interest, Fee and Commisson Income | D14: =D13+D10 -> 13180515 | E14: =E13+E10 -> 10269754
B15: Other Income | C15: 4.26 | D15: ='4.22-4.33'!D81 -> 359663.48 | E15: ='4.22-4.33'!E81 -> 461967.88
B16: Total Operating Income | D16: =SUM(D14:D15) -> 13540178 | E16: =SUM(E14:E15) -> 10731722
B17: Impairment (Charge)/ Reversal for Loans and Other Losses | C17: 4.27 | D17: =-'4.22-4.33'!D92 -> -443793.17 | E17: =-'4.22-4.33'!E92 -> -479480.17
B18: Net Operating Income | D18: =SUM(D16:D17) -> 13096385 | E18: =SUM(E16:E17) -> 10252242
B19: Operating Expense
B20: Employment Benefit Expenses | C20: 4.28 | D20: =-'4.22-4.33'!D112 -> -3758530.3 | E20: =-'4.22-4.33'!E112 -> -3111784.2
B21: Other Administrative and Operating Expenses | C21: 4.29 | D21: =-'4.22-4.33'!D143 -> -2427519.9 | E21: =-'4.22-4.33'!E143 -> -2309074.5
B22: Depreciation, Amortisation and Impairment | C22: 4.3 | D22: =-'4.22-4.33'!D151 -> -1366328.3 | E22: =-'4.22-4.33'!E151 -> -1064924.1
B23: Operating Profit | D23: =SUM(D18:D22) -> 5544006.8 | E23: =SUM(E18:E22) -> 3766458.8
B24: Non Operating Income | C24: 4.31 | D24: ='4.22-4.33'!D158 -> 0 | E24: ='4.22-4.33'!E158 -> 0
B25: Non Operating Expense | C25: 4.32 | D25: ='4.22-4.33'!D168 -> 301439.05 | E25: ='4.22-4.33'!E168 -> 60180.281
B26: Profit Before Income Tax | D26: =D23+D24-D25 -> 5242567.8 | E26: =E23+E24-E25 -> 3706278.5 | F26: Profit before tax | J26: =D26 -> 5242567.8 | K26: =E26 -> 3706278.5
B27: Income Tax Expense | C27: 4.33 | F27: Bonus provision | J27: ='4.22-4.33'!D104 -> 582507.53 | K27: ='4.22-4.33'!E104 -> 411808.73
B28: Current Tax Expense | D28: =-SUM('4.22-4.33'!D174:D175) -> -1154998.2 | E28: =-SUM('4.22-4.33'!E174:E175) -> -788696.18 | F28: Profit before bonus | J28: =SUM(J26:J27) -> 5825075.3 | K28: =SUM(K26:K27) -> 4118087.3
B29: Deferred Tax | D29: =-SUM('4.22-4.33'!D177) -> 157239.44 | E29: =-SUM('4.22-4.33'!E177) -> 700420.06 | J29: =J28*0.1 -> 582507.53 | K29: =K28*0.1 -> 411808.73
B30: Profit for the Year | D30: =SUM(D26:D29) -> 4244809 | E30: =SUM(E26:E29) -> 3618002.4 | F30: Check | J30: =J29-'4.22-4.33'!D104 -> 0 | K30: =K29-'4.22-4.33'!E104 -> 0
E32: As per our report of even date

Sheet SoCI
B1: =SoPL!B1 -> ABC Savings and Credit Cooperative Limited
B2: Statement of Comprehensive Income
B3: For the year ended 32nd Ashadh, 2082
D5: =SoPL!E5 -> Amount in NPR
D6: Restated
B7: Particulars | C7: FY 2081/82 | D7: FY 2080/81
B8: Profit for the year | C8: =SoPL!D30 -> 4244809 | D8: =SoPL!E30 -> 3618002.4
B9: Other Comprehensive Income, net of income tax
B10: a) Items that will not subsequently be reclassified to profit or loss
B11: Gains/(losses) on revaluation of property, plant and equipment | C11: ='4.8'!C21 -> 1371969.2 | D11: ='4.8'!D21 -> 0
B12: Actuarial gains/(losses) on defined benefit plans | C12: 0 | D12: 0
B13: Income tax relating to above items | C13: =-SUM(C11:C12)*0.2 -> -274393.84 | D13: =-D12*0.2 -> 0
B15: Net other comprehensive income that will not be reclassified to profit or loss | C15: =SUM(C11:C13) -> 1097575.4 | D15: =SUM(D11:D13) -> 0
B16: b) Items that are or may subsequently be reclassified to profit or loss
B17: Exchange difference on translation of financial assets of foreign operation) | C17: 0 | D17: 0
B18: Income tax relating to above items
B19: Reclassify to profit or loss
B20: Net other comprehensive income that are or may be reclassified to profit or loss | C20: =SUM(C17:C19) -> 0 | D20: =SUM(D17:D19) -> 0
B22: Other Comprehensive Income for the year, Net of Income Tax | C22: =SUM(C15:C21) -> 1097575.4 | D22: =SUM(D15:D21) -> 0
B23: Total Comprehensive Income for the Year | C23: =C22+C8 -> 5342384.4 | D23: =D22+D8 -> 3618002.4
C25: As per our report of even date

Sheet SoCF
B1: =SoCI!B1 -> ABC Savings and Credit Cooperative Limited
B2: Statement of Cash Flows
B3: For the year ended 32nd Ashadh, 2082 | I3: FY 2080-81 | L3: FY 2081-82
D4: =SoCI!D5 -> Amount in NPR | F4: Net Profit | I4: =SoPL!E26+SoCI!D12 -> 3706278.5 | K4: Net Profit | L4: =SoCI!C23+SUM(P6:P8)+P9+P10+P11+P12+P13+P14 -> 6902689.2 | N4: Net Profit | P4: =SoCI!C23 -> 5342384.4 | Q4: =SoCI!D23 -> 3618002.4
D5: Restated | F5: add: depreciation | I5: =-SoPL!E22-I7 -> 1064924.1 | N5: adjustment:
B6: Particulars | C6: =SoPL!D7 -> FY 2081/82 | D6: =SoPL!E7 -> FY 2080/81 | F6: Add: loan loss prov | I6: =-SoPL!E17 -> 479480.17 | N6: Revaluation | P6: =-SoCI!C11 -> -1371969.2 | Q6: =-SoCI!D11 -> 0
B7: CASH FLOWS FROM OPERATING ACTIVITIES | F7: Add: Dep on ROU | I7: 0 | N7: OCI | P7: =-SoCI!C12 -> 0
B8: Interest received | C8: =SoPL!D8-'4.22-4.33'!D103 -> 18242881 | D8: =SoPL!E8-'4.22-4.33'!E103 -> 15123832 | F8: loans to member | I8: =SoFP!F10-SoFP!E10-I6 -> -2565117.3 | K8: loans to member | L8: =SoFP!E10-SoFP!D10-P11 -> -2220504.2 | N8: deferred tax | P8: =-SoCI!C13 -> 274393.84 | Q8: =-SoCI!D13 -> 0
B9: Fee and other operating income received | C9: =SoPL!D11 -> 2239352.8 | D9: =SoPL!E11 -> 1666057.5 | F9: loans to staff | I9: =SoFP!F11-SoFP!E11 -> -521162.97 | K9: loans to staff | L9: =SoFP!E11-SoFP!D11 -> -1097719.8 | N9: deferred tax (SoPL) | P9: =-SoPL!D29 -> -157239.44 | Q9: =-SoPL!E29 -> -700420.06
B10: Interest Paid | C10: =SoPL!D9 -> -7819121.1 | D10: =SoPL!E9 -> -6913198.5 | F10: fixed deposits | I10: =SoFP!F9-SoFP!E9 -> -92829.999 | K10: fixed deposits | L10: =SoFP!E9-SoFP!D9 -> -944158.18 | N10: prov for tax | P10: =-SoPL!D28 -> 1154998.2 | Q10: =-SoPL!E28 -> 788696.18
B11: Other Direct Expenses Paid | C11: =SoPL!D12 -> -268855.73 | D11: =SoPL!E12 -> -222747.24 | F11: other assets | I11: =SoFP!F17-SoFP!E17 -> -172194.95 | K11: investments | L11: =SoFP!E12-SoFP!D12 -> -260000 | N11: loan loss provision | P11: =-SoPL!D17 -> 443793.17 | Q11: =-SoPL!E17 -> 479480.17
B12: Cash Payment to Employees | C12: =SoPL!D20+'4.22-4.33'!D103-SoFP!E24+SoFP!D24 -> -2525771.5 | D12: =SoPL!E20+'4.22-4.33'!E103-SoFP!F24+SoFP!E24 -> -2113275.8 | F12: Investment Property | I12: =SoFP!F14-SoFP!E14 -> -1050000 | K12: current tax assets | L12: =SoFP!E13-SoFP!D13-P10 -> -1029351.4 | N12: deferred staff expense | P12: 0
B13: Other Direct Expenses Paid | C13: =SoPL!D21-SoPL!D25 -> -2728959 | D13: =SoPL!E21-SoPL!E25 -> -2369254.7 | F13: tax paid | I13: =SoFP!F13-SoFP!E13-Q10 -> -924712.94 | K13: PPE | L13: =SoFP!E15-SoFP!D15-P6-'4.22-4.33'!D148 -> -1898517.9 | N13: depreciation | P13: =-SoPL!D22 -> 1366328.3 | Q13: =-SoPL!E22 -> 1064924.1
B14: Operating Cash Flows before Changes in Operating Assets and Liabilities | C14: =SUM(C8:C13) -> 7139526.1 | D14: =SUM(D8:D13) -> 5171413.2 | F14: borrowings | I14: =SoFP!E23-SoFP!F23 -> -253000 | K14: Intangible assets | L14: =SoFP!E16-SoFP!D16-'4.22-4.33'!D150 -> -197750 | N14: Fair value gain | P14: =Appropiation!B9 -> -150000
F15: provisions | I15: =SoFP!E24-SoFP!F24 -> 382698.26 | K15: Right of use assets | L15: 0 | N15: Net profit | P15: =SUM(P4:P14) -> 6902689.2 | Q15: =SUM(Q4:Q13) -> 5250682.8
B16: (Increase) Decrease in Operating Assets | K16: other assets | L16: =SoFP!E17-SoFP!D17 -> -4311612 | Q16: =Q15-I4 -> 1544404.3
B17: Placement with Banks and Financial Institutions | C17: =SoFP!E9-SoFP!D9 -> -944158.18 | D17: =SoFP!F9-SoFP!E9 -> -92829.999 | F17: grant liab | I17: =SoFP!E26-SoFP!F26 -> -348540.61 | K17: deposits | L17: =SoFP!D22-SoFP!E22 -> 6797778.3 | M17: ok
B18: Loans and Advances to Members | C18: ='4.1-4.4'!E51-'4.1-4.4'!D51 -> -2220504.2 | D18: ='4.1-4.4'!F51-'4.1-4.4'!E51 -> -2565117.6 | F18: other liab | I18: =(SoFP!E27-'4.11-4.17'!E135)-(SoFP!F27-'4.11-4.17'!F135)-'4.11-4.17'!F135 -> 8426.6502 | K18: Borrowings | L18: =SoFP!D23-SoFP!E23 -> 992500 | M18: ok
B19: Loans and Advances to Staffs | C19: ='4.1-4.4'!E111-'4.1-4.4'!D111 -> -1189272.8 | D19: ='4.1-4.4'!F111-'4.1-4.4'!E111 -> -771525.32 | F19: deposits | I19: =SoFP!E22-SoFP!F22 -> 4626541.7 | K19: Provisions | L19: =SoFP!D24-SoFP!E24-P7 -> 446500.38
B20: Other Assets | C20: =('4.11-4.17'!E16-'4.11-4.17'!E14)-('4.11-4.17'!D16-'4.11-4.17'!D14)+SoFP!E14-SoFP!D14 -> -4370059.1 | D20: =('4.11-4.17'!F16-'4.11-4.17'!F14)-('4.11-4.17'!E16-'4.11-4.17'!E14)+SoFP!F14-SoFP!E14 -> -971832.59 | F20: operating | I20: =SUM(I4:I19) -> 4340790.6 | K20: Deferred tax liab | L20: =SoFP!D25-SoFP!E25-P8-P9 -> 0
F21: purchase of PPE & intangible | I21: =SoFP!F15+SoFP!F16-SoFP!E15-SoFP!E16-I5 -> -1988322.3 | K21: deferred grant | L21: 0
B22: Increase (Decrease) in Operating Liabilities | F22: financing | I22: =D43 -> -1727770.8 | K22: lease liabilities | L22: 0
B23: Deposit from members | C23: =SoFP!D22-SoFP!E22 -> 6797778.3 | D23: =SoFP!E22-SoFP!F22 -> 4626541.7 | K23: other liab | L23: =(SoFP!D27-'4.11-4.17'!D135)-(SoFP!E27-'4.11-4.17'!E135)-SoFP!E26+SoFP!D26-'4.11-4.17'!E135 -> 209535.11
B24: Borrowings | C24: =SoFP!D23-SoFP!E23 -> 992500 | D24: =SoFP!E23-SoFP!F23 -> -253000 | F24: change | I24: =SUM(I20:I22) -> 624697.47
B25: Other Liabilities | C25: =(SoFP!D27-'4.11-4.17'!D135)+SoFP!D26-SoFP!E26-(SoFP!E27-'4.11-4.17'!E135)+SoCI!C12-'4.11-4.17'!D108-'4.11-4.17'!E135 -> 293594.96 | D25: =(SoFP!E27-'4.11-4.17'!E135)+SoFP!E26-SoFP!F26-(SoFP!F27-'4.11-4.17'!F135)+SoCI!D12-'4.11-4.17'!E108-'4.11-4.17'!F135 -> -253998.96 | F25: opening | I25: =SoFP!F8 -> 6246974.7 | K25: equity | L25: =C43 -> -2618433.1
B26: Net Cash Flow from Operating Activities before Tax Paid | C26: =C14+SUM(C17:C25) -> 6499405.1 | D26: =D14+SUM(D17:D25) -> 4889650.4
B27: Income Tax Paid | C27: =SoFP!E13-SoFP!D13+SoPL!D28 -> -1029351.4 | D27: =SoFP!F13-SoFP!E13+SoPL!E28 -> -924712.94 | F27: closing | I27: =SUM(I24:I25) -> 6871672.2
B28: Net Cash Flow from Operating Activities | C28: =SUM(C26:C27) -> 5470053.7 | D28: =SUM(D26:D27) -> 3964937.4 | I28: =I27-SoFP!E8 -> -1.1175871e-08 | K28: Total change | L28: =SUM(L4:L25) -> 770956.42
K29: opening | L29: =SoFP!E8 -> 6871672.2
B30: CASH FLOWS FROM INVESTING ACTIVITIES | K30: closing | L30: =L29+L28 -> 7642628.6
B31: Purchase of Property and Equipment | C31: =SoFP!E15-SoFP!D15+SoCI!C11-'4.22-4.33'!D148 -> -1898517.9 | D31: =SoFP!F15-SoFP!E15+SoCI!D11-'4.22-4.33'!E148 -> -1850458.6
B32: Receipts from Sale of Property and Equipment | C32: 0 | D32: 0 | K32: difference | L32: =L30-SoFP!D8 -> 1.6763806e-08
B33: Purchse of Investment Securities | C33: =SoFP!E12-SoFP!D12 -> -260000 | D33: =SoFP!F12-SoFP!E12 -> 0
B34: Purchase of Intangible Assets | C34: =SoFP!E16-SoFP!D16-'4.22-4.33'!D150 -> -197750 | D34: =SoFP!F16-SoFP!E16-'4.22-4.33'!E150 -> -137863.72
B35: Dividend and patronage refund received | C35: =SoPL!D15-'4.22-4.33'!D75 -> 275603.64 | D35: =SoPL!E15-'4.22-4.33'!E75 -> 375852.88
B36: Net Cash Used in Investing Activities | C36: =SUM(C31:C35) -> -2080664.2 | D36: =SUM(D31:D35) -> -1612469.5
B38: CASH FLOWS FROM FINANCING ACTIVITIES
B39: Receipt from Issue of Shares | C39: =SoFP!D30-SoFP!E30 -> 1500000 | D39: =SoFP!E30-SoFP!F30 -> 1954000
B40: Dividends Paid | C40: =SoCE!H43 -> -3466583.6 | D40: =SoCE!H23 -> -2736482.6
B41: Patronage refund payment | C41: =SoCE!F42 -> -532538.05 | D41: =SoCE!F22 -> -520421.42
B42: Other Receipts/Payments | C42: =SoCE!H37 -> -119311.38 | D42: =SoCE!H17 -> -424866.8
B43: Net Cash from Financing Activities | C43: =SUM(C39:C42) -> -2618433.1 | D43: =SUM(D39:D42) -> -1727770.8
B44: Net Increase (Decrease) in Cash and Cash Equivalents | C44: =C43+C36+C28+0.78 -> 770957.2 | D44: =D43+D36+D28 -> 624697.19
B45: Cash and Cash Equivalents (opening) | C45: =SoFP!E8 -> 6871672.2 | D45: =SoFP!F8 -> 6246974.7
B46: Effect of Exchange difference on cash and cash equivalents held | D46: 0
B47: Cash and Cash Equivalents (closing) | C47: =SUM(C44:C46) -> 7642629.4 | D47: =SUM(D44:D46) -> 6871671.9 | F47: =C47-SoFP!D8 -> 0.78000003 | G47: =D47-C45 -> -0.28139802

Sheet SoCE
B1: =SoCF!B1 -> ABC Savings and Credit Cooperative Limited
B2: Statement of Changes in Equity
B3: For the year ended 32nd Ashadh, 2082
J4: =SoCF!D4 -> Amount in NPR
B5: Particulars | C5: Share Capital | D5: General Reserve | E5: Revaluation Reserve | F5: Patronage Refund Reserve | G5: Fair Value Reserve | H5: *Other Statutory Reserves | I5: Retained Earnings | J5: Total | L5: Reconciliation of Retained Earnings | Q5: 10
B6: Balance as at 1st Shrawan 2080 | C6: ='4.11-4.17'!F144 -> 13732000 | D6: ='4.18-4.21'!F13 -> 7076728.8 | E6: 0 | F6: 570291.02 | G6: 0 | H6: ='Other Reserve'!J6 -> 9391418.9 | I6: 0 | J6: =SUM(C6:I6) -> 30770439 | L6: Retained Earnings as per GAAP | P6: 0
B7: Adjustment/Restatement on transition to NFRS for SMEs | C7: 0 | D7: 0 | E7: ='4.8'!C10+'4.10'!K64 -> 2730846.1 | F7: 0 | G7: ='4.6-4.7'!F24 -> 300000 | H7: 0 | I7: =P12 -> -2495355.1 | J7: =SUM(C7:I7) -> 535490.94 | L7: Revaluation of gratuity | P7: =-'4.11-4.17'!F53 -> -1709605.1 | Q7: =-EN_SoFP!C100 -> -1709605.1
B8: Restated Balance as at Shrawan 01, 2080 | C8: =C6+C7 -> 13732000 | D8: =D6+D7 -> 7076728.8 | E8: =E6+E7 -> 2730846.1 | F8: =F6+F7 -> 570291.02 | G8: =G6+G7 -> 300000 | H8: =H6+H7 -> 9391418.9 | I8: =I6+I7 -> -2495355.1 | J8: =J6+J7 -> 31305930 | L8: Revaluation of leave benefits | P8: =-'4.11-4.17'!F54 -> -403900 | Q8: =-EN_SoFP!C110 -> -403900
B9: Comprehensive Income for the year | L9: Deferred taxes | P9: ='4.10'!I82 -> -381850.03 | Q9: ='4.10'!I82 -> -381850.03
B10: Profit for the year | C10: 0 | I10: =SoPL!E30 -> 3618002.4 | J10: =SUM(C10:I10) -> 3618002.4 | L10: Interest Receviable | P10: 0
B11: Other Comprehensive Income, Net of Tax | C11: =SUM(C12:C13) -> 0 | D11: =SUM(D12:D13) -> 0 | E11: =SUM(E12:E13) -> 0 | F11: =SUM(F12:F13) -> 0 | G11: =SUM(G12:G13) -> 0 | H11: =SUM(H12:H13) -> 0 | I11: =SUM(I12:I13) -> 0 | J11: =SUM(C11:I11) -> 0
B12: Gains/(losses) on revaluation | C12: 0 | J12: =SUM(C12:I12) -> 0 | L12: Retained Earnings as per NFRS | P12: =SUM(P6:P11) -> -2495355.1 | Q12: =SUM(Q6:Q11) -> -2495355.1
B13: Actuarial gains/(losses) on defined benefit plans | C13: 0 | I13: =SoCI!D15 -> 0 | J13: =SUM(C13:I13) -> 0
B14: Total Comprehensive Income for the year | C14: =SUM(C10:C11) -> 0 | D14: =SUM(D10:D11) -> 0 | E14: =SUM(E10:E11) -> 0 | F14: =SUM(F10:F11) -> 0 | G14: =SUM(G10:G11) -> 0 | H14: =SUM(H10:H11) -> 0 | I14: =SUM(I10:I11) -> 3618002.4 | J14: =SUM(J10:J11) -> 3618002.4
B15: Transfer to Reserves during the year | C15: 0 | D15: =SUM('4.18-4.21'!E9:E10) -> 827156.4 | E15: 0 | F15: =Appropiation!C16 -> 555781.05 | G15: ='4.6-4.7'!E24 -> 250000 | H15: ='Other Reserve'!J7 -> 1656227.5 | I15: =-SUM(C15:H15)-Appropiation!C17 -> -3300280.6 | J15: =SUM(C15:I15) -> -11115.621
B16: Transfer from Reserves during the year | C16: 0 | D16: ='4.18-4.21'!E11 -> 49869.6 | E16: 0 | F16: =-'4.18-4.21'!E11 -> -49869.6 | G16: 0 | H16: ='Other Reserve'!J8 -> 0 | I16: 0 | J16: =SUM(C16:I16) -> 0
B17: Expense from the Fund | C17: 0 | D17: 0 | F17: 0 | G17: 0 | H17: =+'Other Reserve'!H9 -> -424866.8 | I17: 0 | J17: =SUM(C17:I17) -> -424866.8
B18: Transactions with Owners, directly recognized in Equity | J18: =SUM(C18:H18) -> 0
B19: Share Issued | C19: ='4.11-4.17'!E142 -> 2325000 | J19: =SUM(C19:H19) -> 2325000
B20: Share redemption | C20: ='4.11-4.17'!E143 -> -371000 | J20: =SUM(C20:I20) -> -371000
B21: Dividend to Equity-Holders | C21: 0 | D21: 0 | E21: 0 | F21: 0 | G21: 0 | H21: 0 | I21: 0 | J21: =SUM(C21:I21) -> 0
B22: Patronage Refund paid | C22: 0 | D22: 0 | E22: 0 | F22: =-F8-F16 -> -520421.42 | G22: 0 | H22: 0 | I22: 0 | J22: =SUM(C22:I22) -> -520421.42
B23: Cash Dividend paid | C23: 0 | D23: 0 | E23: 0 | F23: 0 | G23: 0 | H23: ='Other Reserve'!J9-H17 -> -2736482.6 | I23: 0 | J23: =SUM(C23:I23) -> -2736482.6
B24: Other | C24: 0 | D24: 0 | E24: 0 | F24: 0 | G24: 0 | H24: 0 | I24: 0 | J24: =SUM(C24:I24) -> 0
B25: Balance at Ashadh 31, 2081 | C25: =SUM(C14:C24,C8) -> 15686000 | D25: =SUM(D14:D24,D8) -> 7953754.8 | E25: =SUM(E14:E24,E8) -> 2730846.1 | F25: =SUM(F14:F24,F8) -> 555781.05 | G25: =SUM(G14:G24,G8) -> 550000 | H25: =SUM(H14:H24,H8) -> 7886297.1 | I25: =SUM(I14:I24,I8) -> -2177633.3 | J25: =SUM(J14:J24,J8) -> 33185046
B28: Balance as at 1st Shrawan 2081 | C28: =C25 -> 15686000 | D28: =D25 -> 7953754.8 | E28: =E25 -> 2730846.1 | F28: =F25 -> 555781.05 | G28: =G25 -> 550000 | H28: =H25 -> 7886297.1 | I28: =I25 -> -2177633.3 | J28: =J25 -> 33185046
B29: Comprehensive Income for the year
B30: Profit for the year | C30: 0 | D30: 0 | E30: 0 | F30: 0 | G30: 0 | H30: 0 | I30: =SoPL!D30 -> 4244809 | J30: =SUM(C30:I30) -> 4244809
B31: Other Comprehensive Income, Net of Tax | C31: 0 | D31: 0 | E31: =SUM(E32:E33) -> 1097575.4 | F31: 0 | G31: 0 | H31: 0 | I31: =SUM(I32:I33) -> 0 | J31: =SUM(C31:I31) -> 1097575.4
B32: Gains/(losses) on revaluation of property, plant and equipment | E32: =SoCI!C11-SoCI!C11*0.2 -> 1097575.4 | J32: =SUM(C32:I32) -> 1097575.4
B33: Actuarial gains/(losses) on defined benefit plans | F33: =SoCI!D28 -> 0 | G33: =SoCI!E28 -> 0 | I33: =SoCI!C12-SoCI!C12*0.2 -> 0 | J33: =SUM(C33:I33) -> 0
B34: Total Comprehensive Income for the year | C34: =C30+C31 -> 0 | D34: =D30+D31 -> 0 | E34: =E30+E31 -> 1097575.4 | F34: =F30+F31 -> 0 | G34: =G30+G31 -> 0 | H34: =H30+H31 -> 0 | I34: =I30+I31 -> 4244809 | J34: =SUM(J30:J31) -> 5342384.4
B35: Transfer to Reserves during the year | C35: 0 | D35: =SUM('4.18-4.21'!D9:D10) -> 1124247.1 | E35: 0 | F35: =Appropiation!B16 -> 198232.14 | G35: =-Appropiation!B9 -> 150000 | H35: ='Other Reserve'!J12 -> 590731.77 | I35: =-SUM(C35:H35)-Appropiation!B17 -> -2067175.7 | J35: =SUM(C35:I35) -> -3964.6427
B36: Transfer from Reserves during the year | C36: 0 | D36: =-(H36+F36) -> 23243 | E36: 0 | F36: -23243 | H36: ='Other Reserve'!C15 -> 0 | I36: 0 | J36: =SUM(C36:I36) -> 0
B37: Expense from the Fund | C37: 0 | D37: 0 | E37: 0 | F37: 0 | H37: =+'Other Reserve'!G14+'Other Reserve'!H14 -> -119311.38 | I37: 0 | J37: =SUM(C37:I37) -> -119311.38
B38: Transactions with Owners, directly recognized in Equity | J38: =SUM(C38:I38) -> 0
B39: Share Issued | C39: ='4.11-4.17'!D142 -> 2306000 | D39: 0 | E39: 0 | F39: 0 | H39: 0 | I39: 0 | J39: =SUM(C39:I39) -> 2306000
B40: Share Redemption | C40: ='4.11-4.17'!D143 -> -806000 | D40: 0 | E40: 0 | F40: 0 | H40: 0 | I40: 0 | J40: =SUM(C40:I40) -> -806000
B41: Dividend to Equity-Holders | J41: =SUM(C41:I41) -> 0
B42: Patronage refund paid | C42: 0 | D42: 0 | E42: 0 | F42: =-(F28+F36) -> -532538.05 | H42: 0 | I42: 0 | J42: =SUM(C42:I42) -> -532538.05
B43: Cash Dividend Paid | C43: 0 | D43: 0 | E43: 0 | F43: 0 | H43: ='Other Reserve'!J14-H37 -> -3466583.6 | I43: 0 | J43: =SUM(C43:I43) -> -3466583.6
B44: Other | C44: 0 | D44: 0 | E44: 0 | F44: 0 | H44: 0 | I44: 0 | J44: =SUM(C44:I44) -> 0
B45: Balance at Ashadh 32, 2082 | C45: =SUM(C28,C34:C44) -> 17186000 | D45: =SUM(D28,D34:D44) -> 9101245 | E45: =SUM(E28,E34:E44) -> 3828421.4 | F45: =SUM(F28,F34:F44) -> 198232.14 | G45: =SUM(G28,G34:G44) -> 700000 | H45: =SUM(H28,H34:H44) -> 4891133.9 | I45: =ROUND(SUM(I28,I34:I44),2) -> 0 | J45: =SUM(J28,J34:J44) -> 35905032

Sheet Other Reserve
B1: =SoCF!B1 -> ABC Savings and Credit Cooperative Limited
B2: *Other Statutory Reserve and Other Reserves and Funds
B3: For the year ended 32nd Ashadh, 2082
J4: =SoCF!D4 -> Amount in NPR
B5: Particulars | C5: Share Dividend Fund | D5: Cooperative Education Fund | E5: Losses Recovery Fund | F5: Cooperative Development Fund | G5: Community Development Fund | H5: Stablization Fund | I5: Other Risk Management | J5: Total
B6: Balance as at 1st Shrawan 2080 | C6: 6373002 | D6: 645247.3 | E6: 424866.8 | F6: 424866.8 | G6: 424866.8 | H6: 424866.8 | I6: 673702.43 | J6: =SUM(C6:I6) -> 9391418.9
B7: Approriation from the profit | C7: =Appropiation!C19 -> 1159359.3 | D7: =Appropiation!C20 -> 82811.377 | E7: =Appropiation!C21 -> 82811.377 | F7: =Appropiation!C22 -> 82811.377 | G7: =Appropiation!C23 -> 82811.377 | H7: =Appropiation!C24 -> 82811.377 | I7: =Appropiation!C25 -> 82811.377 | J7: =SUM(C7:I7) -> 1656227.5
B8: Transfer to General Fund | C8: 0 | J8: =SUM(C8:I8) -> 0
B9: Expense from the Fund | C9: -2736482.6 | E9: 0 | F9: 0 | G9: 0 | H9: =-H6 -> -424866.8 | J9: =SUM(C9:I9) -> -3161349.4
B10: Other Adjustment | C10: 0 | D10: 0 | E10: 0 | F10: 0 | G10: 0 | H10: 0 | I10: 0 | J10: 0
B11: Balance as at Ashadh 31, 2081 | C11: =SUM(C6:C10) -> 4795878.7 | D11: =SUM(D6:D9) -> 728058.68 | E11: =SUM(E6:E9) -> 507678.18 | F11: =SUM(F6:F9) -> 507678.18 | G11: =SUM(G6:G9) -> 507678.18 | H11: =SUM(H6:H9) -> 82811.377 | I11: =SUM(I6:I9) -> 756513.81 | J11: =SUM(J6:J10) -> 7886297.1
B12: Approriation from the profit | C12: =Appropiation!B19 -> 413512.24 | D12: =Appropiation!B20 -> 29536.588 | E12: =Appropiation!B21 -> 29536.588 | F12: =Appropiation!B22 -> 29536.588 | G12: =Appropiation!B23 -> 29536.588 | H12: =Appropiation!B24 -> 29536.588 | I12: =Appropiation!B25 -> 29536.588 | J12: =SUM(C12:I12) -> 590731.77
B13: Transfer to General Fund | C13: 0 | D13: 0 | E13: 0 | F13: 0 | J13: =SUM(C13:I13) -> 0
B14: Expense from the Fund | C14: -3466583.6 | G14: -36500 | H14: =-H11 -> -82811.377 | I14: 0 | J14: =SUM(C14:I14) -> -3585895
B15: Other Adjustment | C15: 0 | D15: 0 | E15: 0 | F15: 0 | G15: 0 | H15: 0 | I15: 0 | J15: =SUM(C15:I15) -> 0
B16: Balance at Ashadh 32, 2082 | C16: =SUM(C11:C15) -> 1742807.3 | D16: =SUM(D11:D15) -> 757595.27 | E16: =SUM(E11:E15) -> 537214.77 | F16: =SUM(F11:F15) -> 537214.77 | G16: =SUM(G11:G15) -> 500714.77 | H16: =SUM(H11:H15) -> 29536.588 | I16: =SUM(I11:I15) -> 786050.4 | J16: =SUM(J11:J15) -> 4891133.9

Sheet Appropiation
A1: =SoCF!B1 -> ABC Savings and Credit Cooperative Limited
A2: Appropriation of the fund
A3: For the year ended 32nd Ashadh, 2082
C4: =SoCE!J4 -> Amount in NPR
A5: Particulars | B5: =SoCF!C6 -> FY 2081/82 | C5: =SoCF!D6 -> FY 2080/81
A6: Appropriation
A7: Net Profit/Loss for this year | B7: =SoCE!I30 -> 4244809 | C7: ='5.7_NFRS1'!D124 -> 3050280.6
A8: Actuarial Gain/Loss from Defined Benefits Plan | B8: =SoCE!I31 -> 0 | C8: 0
A9: Fair value gain | B9: =-'4.22-4.33'!D76 -> -150000 | C9: 0
A10: TOTAL | B10: =SUM(B7:B9) -> 4094809 | C10: =SUM(C7:C9) -> 3050280.6
A11: Opening Retained Earnings | B11: =SoCE!I28 -> -2177633.3 | C11: 0
A12: Grant income of capital nature | B12: =-'4.22-4.33'!D75 -> -84059.846 | C12: =-'4.22-4.33'!E75 -> -86115
A13: Available profits | B13: =SUM(B10:B12) -> 1833115.8 | C13: =SUM(C10:C12) -> 2964165.6
A14: General Reserve | B14: =(B7+B12)*0.25-B12 -> 1124247.1 | C14: =(C7+C12)*0.25-C12 -> 827156.4
A15: Balance | B15: =B10+B11-B14 -> 792928.55 | C15: =C10+C11-C14 -> 2223124.2
A16: Patronage Refund | B16: =B15*0.25 -> 198232.14 | C16: =C15*0.25 -> 555781.05
A17: Coop promotion fund | B17: =B15*0.5% -> 3964.6427 | C17: =C15*0.5% -> 11115.621
A18: Balance | B18: =B15-B16-B17 -> 590731.77 | C18: =C15-C16-C17 -> 1656227.5
A19: Share Dividend Fund | B19: =B18-SUM(B20:B25) -> 413512.24 | C19: =C18-SUM(C20:C25) -> 1159359.3
A20: Cooperative Education Fund | B20: =B18*5% -> 29536.588 | C20: =C18*5% -> 82811.377
A21: Losses Recovery Fund | B21: =B20 -> 29536.588 | C21: =C20 -> 82811.377
A22: Cooperative Development Fund | B22: =B21 -> 29536.588 | C22: =C21 -> 82811.377
A23: Community Development Fund | B23: =B22 -> 29536.588 | C23: =C22 -> 82811.377
A24: Stablization Fund | B24: =B23 -> 29536.588 | C24: =C23 -> 82811.377
A25: Other Risk Management | B25: =B24 -> 29536.588 | C25: =C24 -> 82811.377
A26: TOTAL | B26: =B18-SUM(B19:B25) -> 0 | C26: =C18-SUM(C19:C25) -> 0

Sheet 4.1-4.4
B1: =Appropiation!A1 -> ABC Savings and Credit Cooperative Limited
B2: Notes to Accounts
B3: =Appropiation!A3 -> For the year ended 32nd Ashadh, 2082
B5: 4. Notes to the Financial Statements
B6: 4.1 Cash and Cash Equivalent
B7: The cash and cash equivalents for the purpose of cash flow statement include cash in hand, balances with banks and financial institutions, and highly liquid financial assets with original maturity of three months or less from the acquisition date that are subject to and insignificant risk of changes in their fair values and are used by the Cooperative in the management of its short-term commitments. Details of Cash and Cash Equivalents are presented hereunder:
B9: Particulars | D9: As at 32nd Ashadh 2082 | E9: As at 31st Ashadh 2081 | F9: As at 1st Shrawan 2080
B10: Cash in Hand | D10: 0 | E10: 0 | F10: 0
B11: Balance with banks (available on demand) | D11: =E11*1.01-4817.28+111132 -> 1575028.8 | E11: =F11*1.1 -> 1454172.3 | F11: 1321974.9
B12: Fixed deposit with banks (original maturity upto 3 months) | D12: =E12*1.12 -> 6067599.8 | E12: =F12*1.1 -> 5417499.8 | F12: 4924999.8
B13: Other | D13: 0 | E13: 0 | F13: 0
B14: Total | D14: =SUM(D10:D13) -> 7642628.6 | E14: =SUM(E10:E13) -> 6871672.2 | F14: =SUM(F10:F13) -> 6246974.7
B17: 4.2 Placements with Financial Instutions
B18: Fixed Deposit placement with financial institutions are financial assets which are measured at amortized cost using the effective interest rate (‘EIR’) method less impairment, if any. The amortization of EIR and loss arising from impairment, if any is recognized in the Statement of Profit or Loss. The details of such financial assets are as follows:
B20: Particulars | D20: =D9 -> As at 32nd Ashadh 2082 | E20: =E9 -> As at 31st Ashadh 2081 | F20: =F9 -> As at 1st Shrawan 2080
B21: Fixed Deposit Placements with Banks and Financial Institutions | D21: =E21*1.01+411131.88-111132+550400 -> 10319988 | E21: =F21*1.01 -> 9375829.9 | F21: =352797999.997079/38+950-900-428-780 -> 9282999.9
B22: Less: Allowances for Impairment | D22: 0 | E22: 0 | F22: 0
B23: Total | D23: =SUM(D21:D22) -> 10319988 | E23: =SUM(E21:E22) -> 9375829.9 | F23: =SUM(F21:F22) -> 9282999.9
B25: 4.3 Loans and Advances to Members
B26: The Cooperative provides various loans and advance facilities to its members. These assets are subsequently measured at amortized cost using the effective interest rate (‘EIR’) method less impairment, if any. The amortization of EIR and loss arising from impairment, if any is recognized in the Statement of Profit and Loss.
B27: The Cooperative has adopted an alternative method for assessment of impairment of loans. Accordingly, individual and collective impairment loss amount calculated as per Section 11 of Financial Instruments is compared with the impairment provision required by prevailing laws.
B29: Impairment as per regulatory requirements:
B30: The Nepal Rastra Bank (NRB) had issued guide line for saving and credit cooperative applicable from current fiscal year. As per Guidelines and Directive for Cooperative engaged in Saving and Credit transactions , 2081 require impairment to be provided for using the following ageing matrix:
B31: Particulars | D31: Provision for Impairment
B32: Good loans (not overdue upto 3 months) | D32: 0.01
B33: Sub-standard loans (overdue for a period form 3 months to 6 months) | D33: 0.25
B34: Doubtful loans (overdue for a period form 6 months to 12 months) | D34: 0.5
B35: Delinquent loans (overdue for more than 12 months) | D35: 1
B37: The details of loans and advances to members has been presented herewith:
B38: Particulars | D38: =D20 -> As at 32nd Ashadh 2082 | E38: =E20 -> As at 31st Ashadh 2081 | F38: =F20 -> As at 1st Shrawan 2080
B39: Land and Housing Loan | D39: =E39*1.02 -> 21456283 | E39: =F39*1.02 -> 21035571 | F39: 20623109
B40: Business Loan | D40: =E40*1.01 -> 89278478 | E40: =F40*1.02 -> 88394533 | F40: 86661307
B41: Saving Loan | D41: =E41*1.02 -> 11564981 | E41: =F41*1.02 -> 11338216 | F41: 11115898
B42: Group Loan | D42: =E42*1.02 -> 2660302.8 | E42: =F42*1.02 -> 2608140 | F42: 2557000
B43: Agriculture Loan | D43: =E43*1.02 -> 3321862.3 | E43: =F43*1.02 -> 3256727.7 | F43: 3192870.3
B44: Home Loan | D44: =E44*1.02 -> 4483219.9 | E44: =F44*1.02 -> 4395313.6 | F44: 4309131
B45: Education Loan | D45: =E45*1.02 -> 3615679.3 | E45: =F45*1.02 -> 3544783.6 | F45: 3475278.1
B46: Micro Loan | D46: =E46*1.02 -> 4472159.4 | E46: =F46*1.02 -> 4384470 | F46: 4298500
B47: Health Loan | D47: =E47*1.02 -> 3474049.7 | E47: =F47*1.02 -> 3405931.1 | F47: 3339148.1
B48: Social Loan | D48: =E48*1.02 -> 4096869.1 | E48: =F48*1.005 -> 4016538.4 | F48: 3996555.6
B49: Total | D49: =SUM(D39:D48) -> 1.4842388e+08 | E49: =SUM(E39:E48) -> 1.4638023e+08 | F49: =SUM(F39:F48) -> 1.435688e+08
B50: Interest Receivable | D50: 1684225 | E50: 1507380 | F50: 1753690
B51: Gross Loans and Advances | D51: =SUM(D49:D50) -> 1.5010811e+08 | E51: =SUM(E49:E50) -> 1.4788761e+08 | F51: =SUM(F49:F50) -> 1.4532249e+08
B52: Less: Allowances for Impairment | D52: =-F104 -> -22975318 | E52: =-E85 -> -22531525 | F52: =-F85 -> -22052044
B53: Total | D53: =SUM(D51:D52) -> 1.2713279e+08 | E53: =SUM(E51:E52) -> 1.2535608e+08 | F53: =SUM(F51:F52) -> 1.2327044e+08
B54: Loans are generally secured against various collaterals including land and building, personal and group guarantee of members, fixed deposits held by the Cooperative and others.
B56: 4.3.1 Allowances for Impairment
B58: Particulars | D58: =D63 -> As at 32nd Ashadh 2082 | E58: =E63 -> As at 31st Ashadh 2081 | F58: =F63 -> As at 1st Shrawan 2080
B59: Impairment as per regulatory requirements | D59: =D69 -> 22975318 | E59: =E69 -> 22531525 | F59: =F69 -> 22052044
B60: Impairment as per section 11 of NFRS for SMEs | D60: 20677786 | E60: 20278372 | F60: 19846840
B61: Provided for (higher of the above) | D61: =D59 -> 22975318 | E61: =E59 -> 22531525 | F61: =F59 -> 22052044
B63: Particulars | D63: =D38 -> As at 32nd Ashadh 2082 | E63: =E38 -> As at 31st Ashadh 2081 | F63: =F38 -> As at 1st Shrawan 2080
B64: Balance at Shrawan 01,2081 | D64: =E69 -> 22531525 | E64: =F69 -> 22052044 | F64: =25609006.312-8000000+753000+7781000-1004000-4950000-1324 -> 20187682
B65: Impairment Losss for the year: | D65: 0 | E65: 0 | F65: 0
B66: Charge for the year | D66: 2278247 | E66: 2218791 | F66: =2679281.88375+789000 -> 3468281.9
B67: Recoveries/Reversal | D67: -1834453.8 | E67: -1739310.8 | F67: -1603919.7
B68: Amount Written Off | D68: 0 | E68: 0 | F68: 0
B69: Balance at Ashadh End | D69: =SUM(D64:D68) -> 22975318 | E69: =SUM(E64:E68) -> 22531525 | F69: =SUM(F64:F68) -> 22052044
B72: 4.3.2 Allowances for Impairment by Loan Ageing as per Regulatory Requirements
B73: 4.3.2.1 Allowances for Impairment by Loan Ageing as per PEARLS Requirements
B74: Particulars | E74: =E63 -> As at 31st Ashadh 2081 | F74: =F63 -> As at 1st Shrawan 2080
B75: Loan Category by Ageing
B76: Good loans (not delinquent) | C76: ='[125]SCH 9-10-11-12-13'!$B$63 -> 1.5677907e+10 | E76: 1.1109872e+08 | F76: 1.0890188e+08
B77: Doubtful loans (delinquent for not more than 12 months) | C77: ='[125]SCH 9-10-11-12-13'!$B$64 -> 65226692 | E77: 21324567 | F77: 21082909
B78: Bad loans (delinquent for more than 12 months) | C78: ='[125]SCH 9-10-11-12-13'!$B$65 -> 66169140 | E78: 13956939 | F78: 13584007
B79: Total | C79: =SUM(C76:C78) -> 1.5809303e+10 | E79: =SUM(E76:E78) -> 1.4638023e+08 | F79: =SUM(F76:F78) -> 1.435688e+08
B81: Impairment Allowances
B82: Good loans (not delinquent) @ 1% | E82: =E76*1% -> 1110987.2 | F82: =F76*1% -> 1089018.8
B83: Doubtful loans (delinquent for not more than 12 months) @ 35% | E83: =E77*35% -> 7463598.5 | F83: =F77*35% -> 7379018.2
B84: Bad loans (delinquent for more than 12 months) @ 100% | E84: =E78 -> 13956939 | F84: =F78 -> 13584007
B85: Allowance for Impairment | E85: =SUM(E82:E84) -> 22531525 | F85: =SUM(F82:F84) -> 22052044
B87: 4.3.2.2 Allowances for Impairment by Loan Ageing as per NRB guideline ( applicable from FY 2081.082)
B88: Particulars | F88: =D63 -> As at 32nd Ashadh 2082
B89: Loan Category by Ageing
B90: Performing Loan
B91: Good loans (not delinquent or deliquent for not more than 3 months) @ 1% | F91: =D40+D39+5500000-400000 -> 1.1583476e+08
B92: Non-Performing Loan
B93: Sub-standard (delinquent for a period from 3 months to 6 months) @ 25% | F93: =SUM(D42:D43) -> 5982165.1
B94: Doubtful loans (delinquent for a peroid from 6 months to 12 months) @ 50% | F94: =SUM(D44:D46) -> 12571059
B95: Bad loans (delinquent for more than 12 months) @ 100% | F95: =D49-F94-F91-F93 -> 14035900
B96: Total | F96: =SUM(F91:F95) -> 1.4842388e+08 | G96: =#REF!-F49 -> #REF!
B97: Impairment Allowances
B98: Performing Loan
B99: Good loans (not delinquent or deliquent by a period upto 3 months) @ 1% | F99: =F91*0.01 -> 1158347.6
B100: Non-Performing Loan
B101: Sub-standard (delinquent for a period from 3 months to 6 months) @ 25% | F101: =F93*0.25 -> 1495541.3
B102: Doubtful loans (delinquent for a peroid from 6 months to 12 months) @ 50% | F102: =F94*0.5 -> 6285529.3
B103: Bad loans (delinquent for more than 12 months) @ 100% | F103: =F95 -> 14035900
B104: Allowance for Impairment | F104: =SUM(F99:F103) -> 22975318
B107: 4.4 Loans and Advances to Staff
B108: The Cooperative provides various loan facilities to its employees as per its by-laws. These loans are provided at concessional rates of interest as compared to market rates. These loans are initially measured at fair values by discounting contractual cash flows at market rate of interest. The difference between the gross amount disbursed and the fair value is recognized as prepaid expense and is amortized to profit or loss over the loan tenure. The amortization of such expenses is presented under "Employement Benefit expenses (Note 4.28)". The unamortized portion of such prepaid expenses is presented under "Other assets (Note 4.11)".
B109: The Cooperative provides Employee Concessional Loan to its staff to meet the financial crisis and other basic needs that will come in the future,after completion of the two years. Vehicle loans are secured against the respective vehicles and property loans are secured against the respective properties. The loans are repayable on EMI (Equated monthly instalment) basis and deducted against salary payable to staff each month. None of the loans are impaired as per the assessment of management. The details of loans are presented hereunder:
B110: Particulars | D110: ='4.1-4.4'!F88 -> As at 32nd Ashadh 2082 | E110: =E74 -> As at 31st Ashadh 2081 | F110: =F74 -> As at 1st Shrawan 2080
B111: Loans to staff (gross outstanding) | D111: 6702071.5 | E111: 5512798.7 | F111: 4741273.4
B112: Fair Value adjustment (related to concessional rate of interest) | D112: -1624052.9 | E112: -1532500 | F112: -1282137.6
B113: Amortized cost of loans and advances to staff | D113: =SUM(D111:D112) -> 5078018.6 | E113: =SUM(E111:E112) -> 3980298.8 | F113: =SUM(F111:F112) -> 3459135.8
B114: Less: Impairment Allowances
B115: Collective Impairment | D115: 0 | E115: 0 | F115: 0
B116: Individual Impairment | D116: 0 | E116: 0 | F116: 0
D117: =SUM(D113:D116) -> 5078018.6 | E117: =SUM(E113:E116) -> 3980298.8 | F117: =SUM(F113:F116) -> 3459135.8

Sheet 4.5
B1: ='4.1-4.4'!B1 -> ABC Savings and Credit Cooperative Limited
B2: ='4.1-4.4'!B2 -> Notes to Accounts
B3: ='4.1-4.4'!B3 -> For the year ended 32nd Ashadh, 2082
B5: 4.5 Investment Securities
B6: The Cooperative has made investment in equity instruments of certain entities which are held as long-term strategic investments and not for trading. The cooperative measures the investments at fair value if the fair value can not be determined without undue cost and efforts. If the fair values cannot be so determined, they are measured at cost less impairment. Since the investments currently held are unlisted, they have been measured at cost less impairment.
B7: Particulars | E7: As at 32nd Ashadh 2082 | H7: As at 31st Ashadh 2081 | K7: As at 1st Shrawan 2080
B9: Investment in equity measured at cost less impairment | E9: =E31 -> 1211000 | H9: =H31 -> 951000 | K9: =K31 -> 951000
B10: Total | E10: =SUM(E8:E9) -> 1211000 | H10: =SUM(H8:H9) -> 951000 | K10: =SUM(K8:K9) -> 951000
B13: 4.5.1: Investment in equity measured at cost
B14: Particulars | E14: =E7 -> As at 32nd Ashadh 2082 | H14: =H7 -> As at 31st Ashadh 2081 | K14: =K7 -> As at 1st Shrawan 2080
B15: Equity Instruments
B16: Quoted Equity Securities | E16: 0 | H16: 0 | K16: 0
B17: Unquoted Equity Securities | E17: =E9 -> 1211000 | H17: ='4.5'!H10 -> 951000 | K17: ='4.5'!K9 -> 951000
B18: Total | E18: =SUM(E15:E17) -> 1211000 | H18: =SUM(H15:H17) -> 951000 | K18: =SUM(K15:K17) -> 951000
B20: 4.5.3: Information relating to Investment in Equities
B21: Particulars | D21: =E14 -> As at 32nd Ashadh 2082 | G21: =H14 -> As at 31st Ashadh 2081 | J21: =K14 -> As at 1st Shrawan 2080
E22: Cost | H22: Cost | K22: Cost
B24: Investment in Unquoted Equity
B25: National Cooperative Bank Limited | E25: 301000 | H25: 301000 | K25: 301000
B26: 3,010 shares of 100 each
B27: Nepal Federation of Saving and Credit Cooperative Union Limited | E27: 810000 | H27: 600000 | K27: 600000
B28: 8,100 shares of 100 each
B29: District Cooperative Union | E29: 100000 | H29: 50000 | K29: 50000
B30: 1000 shares of 100 each
B31: Total | E31: =SUM(E25:E30) -> 1211000 | F31: =SUM(F25:F30) -> 0 | H31: =SUM(H25:H30) -> 951000 | I31: =SUM(I25:I30) -> 0 | K31: =SUM(K25:K30) -> 951000

Sheet 4.6-4.7
B1: ='4.5'!B1 -> ABC Savings and Credit Cooperative Limited
B2: ='4.5'!B2 -> Notes to Accounts
B3: ='4.5'!B3 -> For the year ended 32nd Ashadh, 2082
B5: 4.6 Current Tax Assets
B6: Particulars | D6: ='4.5'!D21:E21 -> As at 32nd Ashadh 2082 | E6: ='4.5'!H14 -> As at 31st Ashadh 2081 | F6: ='4.5'!K14 -> As at 1st Shrawan 2080
B7: Current Tax Assets
B8: Current year Income Tax Assets | D8: 1029351.4 | E8: =4623564.6805/5 -> 924712.94 | F8: =5543151.8/10 -> 554315.18
B9: Tax Assets of Prior Periods | D9: =E14 -> 842646.05 | E9: =F14 -> 706629.3 | F9: =2498052/5 -> 499610.4
B11: Current Tax Liabilities
B12: Current year Income Tax Liabilities | D12: ='4.22-4.33'!D174 -> 1154998.2 | E12: ='4.22-4.33'!E174 -> 788696.18 | F12: =1736481.4/5 -> 347296.28
B13: Tax Liabilities of Prior Periods | D13: ='4.22-4.33'!D175 -> 0 | E13: 0 | F13: 0
B14: Total | D14: =SUM(D8:D9)-SUM(D12:D13) -> 716999.27 | E14: =SUM(E8:E9)-SUM(E12:E13) -> 842646.05 | F14: =SUM(F8:F9)-SUM(F12:F13) -> 706629.3
B17: 4.7 Investment Properties
B18: Investment properties are land and/or building held for capital appreciation or for earning rentals. The Cooperative generally provides loans and advances to its members against collateral of land and/or building. Such properties are put up for sale through auction for recovery of loans in case of default. Sometimes, the properties may not be so realized; in which case the Cooperative assumes ownership of the properties according to the prevailing laws. Such properties are generally held for sale and not for use and are classfied as investment properties.
B19: The Cooperative measures its investment properties using the fair value. The properties are initially measured at cost and subsequntly at fair values at each reporting dates, with differences transferred to profit or loss.
B20: Particulars | D20: =D6 -> As at 32nd Ashadh 2082 | E20: =E6 -> As at 31st Ashadh 2081 | F20: =F6 -> As at 1st Shrawan 2080
B21: Investment Properties measured at Fair Value
B22: Balance as on Shrawan 01. | D22: =E26 -> 1984450 | E22: =F26 -> 934450 | F22: 634450
B23: Addition/(Disposal) during the year. | D23: 0 | E23: 800000 | F23: 0
B24: Net Changes in fair value during the year. | D24: 150000 | E24: 250000 | F24: 300000
B25: Adjustment/Transfer. | D25: 0 | E25: 0 | F25: 0
B26: Net Amount | D26: =SUM(D22:D25) -> 2134450 | E26: =SUM(E22:E25) -> 1984450 | F26: =SUM(F22:F25) -> 934450
B28: The details of the investment properties have been mentioned hereunder:
B29: Particulars | D29: Acquisition date | E29: Area | F29: Cost
B30: Land at Luvu Sanagaun, ward No. 3 jha. (Plot number 767) | D30: 2079.03.20 | E30: 693.20 Sq. m. | F30: 634450
B31: Land at Lalitpur , Sisnery, Ward no. 2 | F31: =+E23+F23+D23 -> 800000
B32: Plot number 662 | D32: 2081.03.24 | E32: 193.2 Sq.m.
B33: Plot number 1759 | D33: 2080.06.24 | E33: 750.19 Sq.m
B34: Total | F34: =SUM(F30:F33) -> 1434450

Sheet 4.8
B1: ='4.6-4.7'!B1 -> ABC Savings and Credit Cooperative Limited
B2: ='4.6-4.7'!B2 -> Notes to Accounts
B3: ='4.6-4.7'!B3 -> For the year ended 32nd Ashadh, 2082
B5: 4.8 Property, Plant and Equipment
B7: Particulars | C7: Land | D7: Building | E7: Office Equipments, Computer and Furniture | F7: Vehicles | G7: Safe and Vault | H7: Other Assets | I7: Total
B8: Cost
B9: As on 01 Shrawan 2080 | C9: =17305926.4/2 -> 8652963.2 | D9: =1678241.17647059/1.5 -> 1118827.5 | E9: =6131464.18181818/2 -> 3065732.1 | F9: =4154329.71428571/1.2 -> 3461941.4 | G9: 1429575.8 | H9: 180310 | I9: =SUM(C9:H9) -> 17909350
B10: Adjustments on transition to NFRS for SMEs | C10: 3413557.6 | D10: 0 | E10: 0 | F10: 0 | G10: 0 | H10: 0 | I10: =SUM(C10:H10) -> 3413557.6
B11: Restated balance as on 01 Shrawan 2080 | C11: =SUM(C9:C10) -> 12066521 | D11: =SUM(D9:D10) -> 1118827.5 | E11: =SUM(E9:E10) -> 3065732.1 | F11: =SUM(F9:F10) -> 3461941.4 | G11: =SUM(G9:G10) -> 1429575.8 | H11: =SUM(H9:H10) -> 180310 | I11: =SUM(C11:H11) -> 21322908
B12: Addition during the year
B13: Acquisition | C13: 0 | D13: 0 | E13: =17032170.58/10 -> 1703217.1 | F13: 402289.38 | G13: 482688 | H13: 0 | I13: =SUM(C13:H13) -> 2588194.4
B14: Disposal during the year | C14: 0 | D14: 0 | E14: -671389.6 | F14: 0 | G14: -59692.59 | H14: -6653.63 | I14: =SUM(C14:H14) -> -737735.82
B15: Adjustment/Revaluation | C15: 0 | D15: 0 | E15: 0 | F15: 0 | G15: 0 | H15: 0 | I15: =SUM(C15:H15) -> 0
B16: Balance as on Ashadh end 2081 | C16: =SUM(C11:C15) -> 12066521 | D16: =SUM(D11:D15) -> 1118827.5 | E16: =SUM(E11:E15) -> 4097559.5 | F16: =SUM(F11:F15) -> 3864230.8 | G16: =SUM(G11:G15) -> 1852571.2 | H16: =SUM(H11:H15) -> 173656.37 | I16: =SUM(I11:I15) -> 23173366
B17: Addition during the Year
B18: Acquisition | C18: 0 | D18: =2262537.5/2 -> 1131268.8 | E18: =2427504.491/5 -> 485500.9 | F18: 324523.33 | G18: 322921.07 | H18: 0 | I18: =SUM(C18:H18) -> 2264214
B19: Capitalization | C19: 0 | D19: 0 | E19: 0 | F19: 0 | G19: 0 | H19: 0 | I19: =SUM(C19:H19) -> 0
B20: Disposal during the year | C20: 0 | D20: =-D16/2 -> -559413.73 | E20: -272090.79 | F20: -21186.39 | G20: 0 | H20: -32196.36 | I20: =SUM(C20:H20) -> -884887.27
B21: Adjustment/Revaluation | C21: =2743938.4/2 -> 1371969.2 | I21: =SUM(C21:H21) -> 1371969.2
B22: Balance as on Ashadh end 2082 | C22: =SUM(C16:C21) -> 13438490 | D22: =SUM(D16:D21) -> 1690682.5 | E22: =SUM(E16:E21) -> 4310969.7 | F22: =SUM(F16:F21) -> 4167567.8 | G22: =SUM(G16:G21) -> 2175492.3 | H22: =SUM(H16:H21) -> 141460.01 | I22: =SUM(I16:I21) -> 25924662
B24: Depreciation and Impairment
B25: As on Shrawan 01 2080 | C25: 0 | D25: 278169 | E25: =3405060.66666667/10 -> 340506.07 | F25: =1323228.33333333/10 -> 132322.83 | G25: 64088 | H25: 32359 | I25: =SUM(C25:H25) -> 847444.9
B26: Depreciation charge for the year | C26: 0 | D26: 128742.09 | E26: =1392152.04/5 -> 278430.41 | F26: 540431.56 | G26: 47749.35 | H26: 13792.98 | I26: =SUM(C26:H26) -> 1009146.4
B27: Impairment for the year | C27: 0 | D27: 0 | E27: 0 | F27: 0 | G27: 0 | H27: 0 | I27: =SUM(C27:H27) -> 0
B28: As on Ashadh end 2081 | C28: =SUM(C25:C27) -> 0 | D28: =SUM(D25:D27) -> 406911.09 | E28: =SUM(E25:E27) -> 618936.47 | F28: =SUM(F25:F27) -> 672754.39 | G28: =SUM(G25:G27) -> 111837.35 | H28: =SUM(H25:H27) -> 46151.98 | I28: =SUM(C28:H28) -> 1856591.3
B29: Depreciation charge for the year | C29: 0 | D29: 112279.99 | E29: =1984891.84/5 -> 396978.37 | F29: 716978.79 | G29: 57761.4 | H29: 11000.47 | I29: =SUM(C29:H29) -> 1294999
B30: Disposals | C30: 0 | D30: =-SUM(D28:D29) -> -519191.08 | E30: 0 | F30: 0 | G30: 0 | H30: 0 | I30: =SUM(C30:H30) -> -519191.08
B31: As on Ashadh end 2082 | C31: =SUM(C28:C30) -> 0 | D31: =SUM(D28:D30) -> 0 | E31: =SUM(E28:E30) -> 1015914.8 | F31: =SUM(F28:F30) -> 1389733.2 | G31: =SUM(G28:G30) -> 169598.75 | H31: =SUM(H28:H30) -> 57152.45 | I31: =SUM(I28:I30) -> 2632399.2
B32: Net Book Value
B33: As on 1 Shrawan 2080 | C33: =C11-C25 -> 12066521 | D33: =D11-D25 -> 840658.45 | E33: =E11-E25 -> 2725226 | F33: =F11-F25 -> 3329618.6 | G33: =G11-G25 -> 1365487.8 | H33: =H11-H25 -> 147951 | I33: =SUM(C33:H33) -> 20475463
B34: As on Ashadh end 2081 | C34: =C16-C28 -> 12066521 | D34: =D16-D28 -> 711916.36 | E34: =E16-E28 -> 3478623.1 | F34: =F16-F28 -> 3191476.4 | G34: =G16-G28 -> 1740733.9 | H34: =H16-H28 -> 127504.39 | I34: =SUM(C34:H34) -> 21316775
B35: As on Ashadh end 2082 | C35: =C22-C31 -> 13438490 | D35: =D22-D31 -> 1690682.5 | E35: =E22-E31 -> 3295054.8 | F35: =F22-F31 -> 2777834.6 | G35: =G22-G31 -> 2005893.6 | H35: =H22-H31 -> 84307.56 | I35: =SUM(C35:H35) -> 23292263

Sheet 4.9
B1: ='4.8'!B1 -> ABC Savings and Credit Cooperative Limited
B2: ='4.8'!B2 -> Notes to Accounts
B3: ='4.8'!B3 -> For the year ended 32nd Ashadh, 2082
B5: 4.9 Goodwill and Intangible Assets
B6: Particulars | C6: Software | D6: Others | E6: Total
B8: Cost
B9: As on Shrawan 01 2080 | C9: =1654940/2 -> 827470 | D9: 0 | E9: =SUM(C9:D9) -> 827470
B10: Addition during the year
B11: Acquisition | C11: =689318.58/5 -> 137863.72 | D11: 0 | E11: =SUM(C11:D11) -> 137863.72
B12: Capitalization | C12: 0 | D12: 0 | E12: =SUM(C12:D12) -> 0
B13: Disposal during the year | C13: 0 | D13: 0 | E13: =SUM(C13:D13) -> 0
B14: Adjustment/Revaluation | C14: 0 | D14: 0 | E14: =SUM(C14:D14) -> 0
B15: Balance as on Ashadh end 2081 | C15: =C9+C11 -> 965333.72 | D15: 0 | E15: =SUM(C15:D15) -> 965333.72
B17: Addition during the Year
B18: Acquisition | C18: 197750 | D18: 0 | E18: =SUM(C18:D18) -> 197750
B19: Capitalization | C19: 0 | D19: 0 | E19: =SUM(C19:D19) -> 0
B20: Disposal during the year | C20: 0 | D20: 0 | E20: =SUM(C20:D20) -> 0
B21: Adjustment/Revaluation | C21: 0 | D21: 0 | E21: =SUM(C21:D21) -> 0
B22: Balance as on Ashadh end 2082 | C22: =C15+SUM(C18:C19)+C20+C21 -> 1163083.7 | D22: =D15+SUM(D18:D19)+D20+D21 -> 0 | E22: =E15+E18+E19+E20+E21 -> 1163083.7
B24: Amortisation and Impairment
B25: As on Shrawan 01, 2080 | C25: =668501/5 -> 133700.2 | D25: 0 | E25: =SUM(C25:D25) -> 133700.2
B26: Amortisation charge for the year | C26: =278888.62/5 -> 55777.724 | D26: 0 | E26: =SUM(C26:D26) -> 55777.724
B27: Impairment for the year | C27: 0 | D27: 0 | E27: =SUM(C27:D27) -> 0
B28: Disposals | C28: 0 | D28: 0 | E28: =SUM(C28:D28) -> 0
B29: Adjustment | C29: 0 | D29: 0 | E29: =SUM(C29:D29) -> 0
B30: As on Ashadh end 2081 | C30: =SUM(C25:C29) -> 189477.92 | D30: =SUM(D25:D29) -> 0 | E30: =SUM(E25:E29) -> 189477.92
B31: Impairment for the year | E31: =SUM(C31:D31) -> 0
B32: Amortisation charge for the year | C32: =356646.28/5 -> 71329.256 | E32: =SUM(C32:D32) -> 71329.256
B33: Disposals | C33: 0 | E33: =SUM(C33:D33) -> 0
B34: Adjustment | C34: 0 | E34: =SUM(C34:D34) -> 0
B35: As on Ashadh end 2082 | C35: =SUM(C30:C34) -> 260807.18 | D35: =SUM(D30:D34) -> 0 | E35: =E30+SUM(E31:E34) -> 260807.18
B36: Net Book Value
B37: As on 1 Shrawan 2080 | C37: =C9-C25 -> 693769.8 | D37: =D9-D25 -> 0 | E37: =SUM(C37:D37) -> 693769.8
B38: As on Ashadh end 2081 | C38: =C15-C30 -> 775855.79 | D38: =D15-D30 -> 0 | E38: =SUM(C38:D38) -> 775855.79
B39: As on Ashadh end 2082 | C39: =C22-C35 -> 902276.54 | D39: =D22-D35 -> 0 | E39: =SUM(C39:D39) -> 902276.54

Sheet 4.10
B1: ='4.9'!B1 -> ABC Savings and Credit Cooperative Limited
B2: ='4.9'!B2 -> Notes to Accounts
B3: ='4.9'!B3 -> For the year ended 32nd Ashadh, 2082
B5: 4.10 Deferred tax assets and liabilities:
B7: Deferred tax is calculated on temporary differences using a tax rate of 20% (FY 2080-81: 20%). Deferred tax assets have been recognized in respect of all tax losses and other temporary differences giving rise to deferred tax assets where the management believe it is probable that these assets will be recovered.
D8: As at | E8: As at
D9: 32nd Ashadh 2082 | E9: 31st Ashad 2081 | G9: 31 Ashadh 2082
B10: Reconciliation of deferred tax assets net
G11: Particulars | H11: Carrying Amount | I11: Tax Base | J11: Difference | K11: DTA/DTL
B12: Opening Balance as at 1st Shrawan | D12: =E16 -> -364141.49 | E12: =K72 -> -1064561.5 | G12: Land | H12: ='4.8'!C35 -> 13438490 | I12: =H12-'4.8'!C10-'4.8'!C21 -> 8652963.2 | J12: =I12-H12 -> -4785526.8 | K12: =J12*0.2 -> -957105.36
B13: Tax income/(expense) during the period recognised in profit or loss | D13: =K24 -> 157239.44 | E13: =K51 -> 700420.06 | G13: PPE_Others | H13: =SoFP!D15-'4.10'!H12 -> 9853773 | I13: =11824413.6571555*0.9 -> 10641972 | J13: =I13-H13 -> 788199.31 | K13: =J13*0.2 -> 157639.86
B14: Tax income/(expense) during the period recognised in OCI | D14: =K25+K26 -> -274393.84 | E14: =K52 -> 0 | G14: Intangible Assets | H14: =SoFP!D16 -> 902276.54 | I14: =+I39+'4.9'!C11 -> 250420.81 | J14: =I14-H14 -> -651855.73 | K14: =J14*0.2 -> -130371.15
G15: Investment Porperty | H15: =H40 -> 1434450 | I15: ='4.6-4.7'!D26 -> 2134450 | J15: =H15-I15 -> -700000 | K15: =J15*0.2 -> -140000
B16: Closing balance as at 32nd Ashad | D16: =SUM(D12:D14) -> -481295.89 | E16: =E12+E13+E14 -> -364141.49 | G16: Prov for Gratuity | H16: ='4.11-4.17'!D53 -> 2361896.3 | I16: 0 | J16: =H16-I16 -> 2361896.3 | K16: =J16*0.2 -> 472379.25
G17: Prov for Leave | H17: ='4.11-4.17'!D54 -> 580807.5 | I17: 0 | J17: =H17-I17 -> 580807.5 | K17: =J17*0.2 -> 116161.5
G18: Provision for expenses | H18: 0 | I18: 0 | J18: 0 | K18: =J18*0.1 -> 0
B19: Details of the deferred tax assets, amounts recognized in profit or loss and amounts recognized in other comprehensive income are as follows: | G19: Deferred tax Asset | H19: =SUM(H12:H18) -> 28571693 | K19: =SUM(K12:K18) -> -481295.89
G20: Opening DTA | K20: =K45 -> -364141.49
G21: Deferred tax expense | K21: =K19-K20 -> -117154.4
B22: Particulars | C22: Asset/ (Liability) | G22: Deferred tax income as per GAAP
C23: As at | D23: As at | E23: As at | G23: Difference
C24: 32nd Ashad 2082 | D24: 31st Ashad 2081 | E24: 1st Shrawan 2080 | G24: Recognized in SoPL | K24: =K21-SUM(K25:K26) -> 157239.44
B25: Property, Plant & Equipment-Land | C25: =K12 -> -957105.36 | D25: =K37 -> -682711.52 | E25: =K64 -> -682711.52 | G25: Recognized in OCI (Revaluation) | K25: =-SoCI!C11*0.2 -> -274393.84
B26: Property, Plant & Equipment-Others | C26: =K13 -> 157639.86 | D26: =K38 -> 61989.095 | E26: =K65 -> -744551.05 | G26: Recognized in OCI | K26: =-SoCI!C12*0.2 -> 0
B27: Intangible Assets | C27: =K14 -> -130371.15 | D27: =K39 -> -132659.74 | E27: 0
B28: Investment Porperty | C28: =K15 -> -140000 | D28: =K40 -> -110000 | E28: =K67 -> -60000
B29: Provision for Gratuity | C29: =K16 -> 472379.25 | D29: =K41 -> 399394.01 | E29: =K68 -> 341921.02
B30: Provision for Leave benefits | C30: =K17 -> 116161.5 | D30: =K42 -> 99846.667 | E30: =K69 -> 80780
C31: =SUM(C25:C30) -> -481295.89 | D31: =SUM(D25:D30) -> -364141.49 | E31: =SUM(E25:E30) -> -1064561.5
B33: Particulars | D33: (Charged)/Credited to Profit or Loss
D34: =C24 -> 32nd Ashad 2082 | E34: =D24 -> 31st Ashad 2081 | G34: 31 Ashadh 2081
B35: Property, Plant & Equipment-Land | D35: 0 | E35: =D25-E25 -> 0
B36: Property, Plant & Equipment-Others | D36: =C26-D26 -> 95650.767 | E36: =D26-E26 -> 806540.15 | G36: Particulars | H36: Carrying Amount | I36: Tax Base | J36: Difference | K36: DTA/DTL
B37: Intangible Assets | D37: =C27-D27 -> 2288.5944 | E37: =D27-E27 -> -132659.74 | G37: Land | H37: ='4.8'!C16 -> 12066521 | I37: =I64 -> 8652963.2 | J37: =I37-H37 -> -3413557.6 | K37: =J37*0.2 -> -682711.52
B38: Investment Porperty | D38: =C28-D28 -> -30000 | E38: =D28-E28 -> -50000 | G38: PPE_Others | H38: ='4.8'!I34-'4.8'!C34 -> 9250254.1 | I38: 9560199.6 | J38: =I38-H38 -> 309945.48 | K38: =J38*0.2 -> 61989.095
B39: Provision for Gratuity | D39: =C29-D29-K26 -> 72985.243 | E39: =D29-E29-E49 -> 57472.986 | G39: Intangible Assets | H39: =SoFP!E16 -> 775855.79 | I39: =1125570.89784836/10 -> 112557.09 | J39: =I39-H39 -> -663298.7 | K39: =J39*0.2 -> -132659.74
B40: Provision for Leave benefits | D40: =C30-D30 -> 16314.833 | E40: =D30-E30 -> 19066.667 | G40: Investment Porperty | H40: =+H67+'4.6-4.7'!E23 -> 1434450 | I40: ='4.6-4.7'!E26 -> 1984450 | J40: =H40-I40 -> -550000 | K40: =J40*0.2 -> -110000
D41: =SUM(D35:D40) -> 157239.44 | E41: =SUM(E35:E40) -> 700420.06 | G41: Prov for Gratuity | H41: ='4.11-4.17'!E53 -> 1996970 | I41: 0 | J41: =H41-I41 -> 1996970 | K41: =J41*0.2 -> 399394.01
G42: Prov for Leave | H42: ='4.11-4.17'!E54 -> 499233.33 | I42: 0 | J42: =H42-I42 -> 499233.33 | K42: =J42*0.2 -> 99846.667
B43: Particulars | D43: (Charged)/Credited to OCI | G43: Carried forward losses | H43: 0 | I43: 0 | J43: =H43-I43 -> 0 | K43: =J43*0.2 -> 0
D44: =D34 -> 32nd Ashad 2082 | E44: =E34 -> 31st Ashad 2081 | G44: Provision for expenses | H44: 0 | I44: 0 | J44: 0 | K44: =J44*0.2 -> 0
B45: Property, Plant & Equipment-Land | D45: =C25-D25 -> -274393.84 | E45: 0 | G45: Deferred tax Asset | H45: =SUM(H37:H44) -> 26023284 | K45: =SUM(K37:K44) -> -364141.49
B46: Property, Plant & Equipment-Others | D46: 0 | E46: 0 | G46: Opening DTA | K46: =K72 -> -1064561.5
B47: Intangible Assets | D47: 0 | E47: 0 | G47: Deferred tax expense | K47: =K45-K46 -> 700420.06
B48: Investment Porperty | D48: 0 | G48: Deferred tax income as per GAAP
B49: Provision for Gratuity | D49: =K26 -> 0 | E49: =K52 -> 0 | G49: Difference
B50: Provision for Leave benefits | D50: 0 | E50: 0
D51: =SUM(D45:D50) -> -274393.84 | E51: =SUM(E45:E50) -> 0 | G51: Recognized in SoPL | K51: =K47-K52 -> 700420.06
G52: Recognized in OCI | K52: =SoCI!D13 -> 0
G61: 1 Shrawan 2080
G63: Particulars | H63: Carrying Amount | I63: Tax Base | J63: Difference | K63: DTA/DTL
G64: Land | H64: ='4.8'!C33 -> 12066521 | I64: ='4.8'!C9 -> 8652963.2 | J64: =I64-H64 -> -3413557.6 | K64: =J64*0.2 -> -682711.52
G65: PPE_Others | H65: ='4.8'!I33-'4.8'!C33 -> 8408941.9 | I65: 4686186.6 | J65: =I65-H65 -> -3722755.3 | K65: =J65*0.2 -> -744551.05
G66: Intangible Assets | H66: =SoFP!F16 -> 693769.8 | I66: =H66 -> 693769.8 | J66: =I66-H66 -> 0 | K66: =J66*0.2 -> 0 | L66: DTL
G67: Investment Porperty | H67: ='4.6-4.7'!F22 -> 634450 | I67: ='4.6-4.7'!F26 -> 934450 | J67: =H67-I67 -> -300000 | K67: =J67*0.2 -> -60000 | L67: DTL
G68: Prov for Gratuity | H68: ='4.11-4.17'!F53 -> 1709605.1 | I68: 0 | J68: =H68-I68 -> 1709605.1 | K68: =J68*0.2 -> 341921.02
G69: Prov for Leave | H69: ='4.11-4.17'!F54 -> 403900 | I69: 0 | J69: =H69-I69 -> 403900 | K69: =J69*0.2 -> 80780 | L69: DTA
G70: Carried forward losses | H70: 0 | I70: 0 | J70: =H70-I70 -> 0 | K70: 0
G71: Provision for expenses | H71: 0 | I71: 0 | J71: =H71-I71 -> 0 | K71: 0 | L71: DTA
G72: Deferred tax Asset | K72: =SUM(K64:K71) -> -1064561.5
G73: DTA as per GAAP | K73: 0 | L73: DTL
G74: Difference | K74: =K72-K73 -> -1064561.5 | L74: DTA
G76: Restatement Entry:
G79: Revaluation Reserve A/c-----Dr | H79: =-K64 -> 682711.52 | K79: Rev reserve
G80: To Deferred tax asset | I80: 0 | K80: To DTl | L80: =-K64 -> 682711.52 | M80: =-K64 -> 682711.52
G81: To Deferred tax liability | I81: =-K72 -> 1064561.5
G82: To Retained Earnings | I82: =H79-SUM(I80:I81) -> -381850.03 | K82: DTA
K83: To R/E | L83: =SUM(K65:K69) -> -381850.03 | M83: =SUM(K65:K70) -> -381850.03
K85: R/E
K86: to DTA | L86: =K73 -> 0 | M86: =L86 -> 0
L88: =L83-L86 -> -381850.03 | M88: =L88 -> -381850.03
L89: =L88-I82 -> 0

Sheet 4.11-4.17
B1: ='4.10'!B1 -> ABC Savings and Credit Cooperative Limited
B2: ='4.10'!B2 -> Notes to Accounts
B3: ='4.10'!B3 -> For the year ended 32nd Ashadh, 2082
B5: 4.11 Other Assets
B6: Particulars | D6: As at 32nd Ashadh 2082 | E6: As at 31st Ashadh 2081 | F6: As at 1st Shrawan 2080
B7: Stock of stationery items | D7: 513259.97 | E7: 453370.9 | F7: =661777.439/2 -> 330888.72
B8: Trade Deposits A | D8: 210941.96 | E8: 29534.83 | F8: 20707.96
B9: Trade Deposits B | D9: 278000 | E9: 40000 | F9: =400000/2 -> 200000
B10: Trade Deposits C | D10: 827962.42 | E10: 363582.19 | F10: =604964.576/2 -> 302482.29
B11: Trade Deposits D | D11: 939535.17 | E11: 93899.517 | F11: 0
B12: Trade Receivables | D12: 822098.09 | E12: 89804.195 | F12: 132873.1
B13: Advances and Prepayments | D13: 1869221.4 | E13: 377138.71 | F13: 267662.59
B14: Prepaid expense related to loans to staff at concessional rates | D14: =-'4.1-4.4'!D112 -> 1624052.9 | E14: =-'4.1-4.4'!E112 -> 1532500 | F14: =-'4.1-4.4'!F112 -> 1282137.6
B15: Other Receivables | D15: 236997.39 | E15: 30626.909 | F15: 301510
B16: Total | D16: =SUM(D7:D15) -> 7322069.3 | E16: =SUM(E7:E15) -> 3010457.2 | F16: =SUM(F7:F15) -> 2838262.3
B18: 4.12 Deposits from Members
B19: Particulars | D19: As at 32nd Ashadh 2082 | E19: As at 31st Ashadh 2081 | F19: As at 1st Shrawan 2080
B20: Regular Monthly Saving | D20: 2271389.1 | E20: 2046424.8 | F20: 1775668.1
B21: Child Saving | D21: 7774117.7 | E21: 7709787.2 | F21: 7413813.3
B22: General Saving | D22: 11565596 | E22: 10583422 | F22: 10072498 | H22: 50000
B23: Fixed Deposit Saving | D23: 73362865 | E23: 72223062 | F23: 70610497
B24: Daily Savings | D24: 11898207 | E24: 11676126 | F24: 11360520
B25: Children Saving | D25: 9808323.5 | E25: 9459231.2 | F25: 9165080.4
B26: Jestha Member Saving | D26: 2290072.1 | E26: 2014922.9 | F26: 1744478.1
B27: Women Saving | D27: 2316330.5 | E27: 2040921.3 | F27: 1819724
B28: Retriement Fund Saving | D28: 3486038.6 | E28: 3199048.1 | F28: 2966384.3
B29: Bill Payment Saving | D29: 2435912.7 | E29: 2159319.5 | F29: 1936950
B30: Education Saving | D30: 5952593.2 | E30: 5591639.9 | F30: 5235250.5
B31: Khutruke Saving | D31: 2347408.3 | E31: 1821691.4 | F31: 1750189.5
B32: Youth Enetreprenure Saving | D32: 2015682.5 | E32: 1493250 | F32: 1425000
B33: Super Special Saving | D33: 1913672.5 | E33: 1292250 | F33: 1325000
B34: Remit Saving | D34: 1837165 | E34: 1166500 | F34: 1250000
B35: Total | D35: =SUM(D20:D34) -> 1.4127537e+08 | E35: =SUM(E20:E34) -> 1.344776e+08 | F35: =SUM(F20:F34) -> 1.2985105e+08
B37: 4.13 Borrowings
B38: Borrowings are financial liabilities measured at amortized cost. The details of borrowings are as follows:
B39: Particulars | D39: As at 32nd Ashadh 2082 | E39: As at 31st Ashadh 2081 | F39: As at 1st Shrawan 2080
B40: Domestic Borrowings
B41: Bank and Financial Institution | D41: 1080000 | E41: 0 | F41: 0
B42: NEFSCUN Loan | D42: 1225000 | E42: 1312500 | F42: 1565500
B43: Total | D43: =SUM(D41:D42) -> 2305000 | E43: =SUM(E41:E42) -> 1312500 | F43: =SUM(F41:F42) -> 1565500
B45: The Cooperative has obtained loans from various banks and financial institutions as mentioned hereunder:
B46: Particulars | D46: Effective Interest Rate | E46: Tenure | F46: Amount
B47: National Co-operative Bank Limited | D47: 0.1 | E47: 1 year | F47: =208000+72000 -> 280000
B48: NABIL Bank Limited | D48: 0.1025 | E48: 1 year | F48: 800000
B49: Total | F49: =SUM(F47:F48) -> 1080000 | H49: =F49-D41 -> 0
B51: 4.14 Provision for Employee Benefits
B52: Particulars | D52: =D39 -> As at 32nd Ashadh 2082 | E52: =E39 -> As at 31st Ashadh 2081 | F52: As at 1st Shrawan 2080
B53: Provision for defined benefit obligations | D53: 2361896.3 | E53: 1996970 | F53: 1709605.1
B54: Provision for other long-term employee benefits | D54: 580807.5 | E54: 499233.33 | F54: 403900
B55: Total | D55: =SUM(D53:D54) -> 2942703.8 | E55: =SUM(E53:E54) -> 2496203.4 | F55: =SUM(F53:F54) -> 2113505.1
H56: Provision for Leave Benefits as at 31 Ashadh 2080
B57: Defined Benefit Obligations
B58: The Cooperative provides a gratuity scheme to its employees which has been classified as a defined benefit plan. The scheme entitles employees to receive payments upon completion of employment as per the Cooperative's employee bylaws. Only those employees who had joined before 15 July 2021 are eligible for this gratuity scheme. Employees who join after that date are eligible for social security fund contributions, which is in the natue of a defined contribution plan. The principal plan provisions are as follows: | H58: S. No. | I58: Name of Staff | J58: Date of Joining | K58: Accumulated Leave (days) | L58: Basic Salary | M58: Leave
B59: Years of service | D59: Gratuity payment rule | H59: 1 | I59: ABC | J59: 61001 | K59: 55 | L59: 78500 | M59: =L59/30*K59 -> 143916.67
B60: More than 5 years and upto 7 years | D60: Last drawn salary x number of years x 1/4 | H60: 2 | I60: XYZ | J60: 61001 | K60: 55 | L60: 72000 | M60: =L60/30*K60 -> 132000
B61: More than 7 years and upto 15 years | D61: Last drawn salary x number of years x 2/4 | H61: 3 | I61: PQR | J61: 61366 | K61: 50 | L61: 33800 | M61: =L61/30*K61 -> 56333.333
B62: More than 15 years and upto 20 years | D62: Last drawn salary x number of years x 3/4 | H62: 4 | I62: WXY | J62: 61366 | K62: 45 | L62: 33800 | M62: =L62/30*K62 -> 50700
B63: More than 20 years | D63: Last drawn salary x number of years x 1
B64: The defined benefit obligations are unfunded. | H64: 5 | I64: UVW | J64: 61732 | K64: 40 | L64: 25600 | M64: =L64/30*K64 -> 34133.333
H65: 6 | I65: IKL | J65: 61732 | K65: 35 | L65: 25600 | M65: =L65/30*K65 -> 29866.667
B66: 4.14.1: Liabilities for employees defined benefit obligation | H66: 7 | I66: LMN | J66: 65384 | K66: 10 | L66: 20800 | M66: =L66/30*K66 -> 6933.3333
B67: Particulars | D67: =D52 -> As at 32nd Ashadh 2082 | E67: =E52 -> As at 31st Ashadh 2081 | F67: =F52 -> As at 1st Shrawan 2080 | H67: 8 | I67: RST | J67: 65384 | K67: 10 | L67: 20800 | M67: =L67/30*K67 -> 6933.3333
B68: Defined benefit obligations | D68: 2361896.3 | E68: 1996970 | F68: 1709605.1 | H68: 9 | I68: EFG | J68: 64654 | K68: 20 | L68: 20000 | M68: =L68/30*K68 -> 13333.333
B69: Fair value of plan assets | I69: TOTAL | M69: =SUM(M59:M68) -> 474150
B70: Recognised liability for defined benefit obligations | D70: =SUM(D68) -> 2361896.3 | E70: =SUM(E68) -> 1996970 | F70: =SUM(F68) -> 1709605.1
H71: Two staff resigned and accumulated leave paid to the staffs: 25,000
B72: 4.14.1.1: Movement in defined benefit obligations
B73: Particulars | E73: FY 2081-82 | F73: FY 2080-81 | H73: Opening balance | J73: 0
B74: Defined benefit obligations at Shrawan 1 | E74: =F77 -> 1996970 | F74: =F68 -> 1709605.1 | H74: Payment | J74: -25000
B75: Provision for the year(recognized in Profit and loss) | E75: 689926.22 | F75: 544364.93 | H75: Balance | J75: =SUM(J73:J74) -> -25000
B76: Payments made | E76: -325000 | F76: -257000 | H76: Closing | J76: =M69 -> 474150
B77: Defined benefit obligations at Ashadh end | E77: =D70 -> 2361896.3 | F77: =E70 -> 1996970 | H77: Expense | J77: =J76-J75 -> 499150
B80: Other Long-Term Employee Benefits
B81: The Cooperative provides two paid leave schemes under this category; namely home leave and sick leave; to its employees.
B82: Home Leave: Employees are entitled to 30 days of paid home leave for each year of service. Unavailed home leaves can be accumulated upto maximum 90 days beyond which the leaves are encashed. Accumulated leaves can be availed at anytime in the future and any leave balance remaining unused are encashed at the time of completion of employment.
B83: Sick Leave: Employees are entitled to 12 days of paid sick leaves for each year of service. Unavailed sick leaves can be accumulated indefinitely. Accumulated leaves can be availed at anytime in the future and any leave balance remaining unused are encashed at the time of completion of employment.
B85: 4.14.2: Other Long-term employee benefit liabilities
B86: Particulars | D86: =D67 -> As at 32nd Ashadh 2082 | E86: =E67 -> As at 31st Ashadh 2081 | F86: =F67 -> As at 1st Shrawan 2080
B87: Other long-term employee benefits | D87: 580807.5 | E87: 499233.33 | F87: 403900
B88: Fair value of plan assets | D88: 0 | E88: 0 | F88: 0
B89: Recognised liability for defined benefit obligations | D89: =D87 -> 580807.5 | E89: =E87 -> 499233.33 | F89: =F87 -> 403900
B91: 4.14.2.1: Movement in Other long-term employee benefits
B92: Particulars | E92: FY 2081-82 | F92: FY 2080-81
B93: Provision as at Shrawan 1 | E93: =F96 -> 499233.33 | F93: =F89 -> 403900
B94: Provision for the year(recognized in Profit and loss) | E94: 99574.167 | F94: 120333.33
B95: Payments made | E95: -18000 | F95: -25000
B96: Provision as at Ashadh end | E96: =SUM(E93:E95) -> 580807.5 | F96: =SUM(F93:F95) -> 499233.33
B98: 4.15 Grant Laibilities
B99: Particulars | D99: =D86 -> As at 32nd Ashadh 2082 | E99: =E86 -> As at 31st Ashadh 2081 | F99: =F86 -> As at 1st Shrawan 2080
B100: Grant Received for Assets (refer 4.15.1) | D100: =D109 -> 444940.15 | E100: =E109 -> 529000 | F100: =F109 -> 615115
B101: Grant Received for Income (refer 4.15.2) | D101: =D124 -> 90000 | E101: =E124 -> 100000 | F101: =F124 -> 362425.61
B102: Total Grant Laibilities | D102: =SUM(D100:D101) -> 534940.15 | E102: =SUM(E100:E101) -> 629000 | F102: =SUM(F100:F101) -> 977540.61
B104: 4.15.1 Grant Received for assets
B105: Particulars | D105: =D86 -> As at 32nd Ashadh 2082 | E105: =E86 -> As at 31st Ashadh 2081 | F105: =F86 -> As at 1st Shrawan 2080
B106: 1. Grant from Department of Cooperative for Assets
B107: Opening Balance in grant income for assets | D107: =E109 -> 529000 | E107: =F109 -> 615115 | F107: 715250
B108: Recognition of income when performance condition are met | D108: -84059.846 | E108: -86115 | F108: -100135
B109: Closing balance in grant for assests | D109: =SUM(D107:D108) -> 444940.15 | E109: =SUM(E107:E108) -> 529000 | F109: =SUM(F107:F108) -> 615115
B112: 4.15.2 Grant Received for Income
B113: Particulars | D113: =D105 -> As at 32nd Ashadh 2082 | E113: =E105 -> As at 31st Ashadh 2081 | F113: =F105 -> As at 1st Shrawan 2080
...

Sheet 4.18-4.21
B1: ='4.11-4.17'!B1 -> ABC Savings and Credit Cooperative Limited
B2: ='4.11-4.17'!B2 -> Notes to Accounts
B3: ='4.11-4.17'!B3 -> For the year ended 32nd Ashadh, 2082
B5: 4.18 General Reserve
B6: General reserve is a statutory reserve required to be maintained as per the Co-operatives Act, 2074. As per the Section 68 of Coooperative Act, the Cooperative needs to transfer 25% of net profits of each year to this reserve. In addition, profit on sale of property, plant and equipment and other fixed assets; amortized portion of grant liabilites in respect of grant received for assets and amount remaining undistributed by the end of the fiscal year out of patronage refund fund appropriated in the immediately preceeding year are also transferred to this reserve.
B7: Particulars | D7: As at 32nd Ashadh 2082 | E7: As at 31st Ashadh 2081 | F7: As at 1st Shrawan 2080
B8: Opening balance | D8: =E13 -> 7953754.8 | E8: =F13 -> 7076728.8 | F8: 5937349.3
B9: Appropriation from net profits for the year | D9: =Appropiation!B14-D10 -> 1040187.3 | E9: =Appropiation!C14-E10 -> 741041.4 | F9: 801940.1
B10: Amortization of grant related to assets | D10: =-Appropiation!B12 -> 84059.846 | E10: =-Appropiation!C12 -> 86115 | F10: 71525
B11: Transfer from Patronage Refund Fund | D11: =SoCE!D36 -> 23243 | E11: 49869.6 | F11: 0
B12: Transfer from Other Reserves and Funds | D12: 0 | E12: 0 | F12: 265914.4
B13: Total | D13: =SUM(D8:D12) -> 9101245 | E13: =SUM(E8:E12) -> 7953754.8 | F13: =SUM(F8:F12) -> 7076728.8 | G13: =F13-SoCE!D8 -> 0
B15: 4.19 Other Statutory Reserves
B16: As per the Co-operatives Act, 2074; out of the profits for a fiscal year remaining after apportionment to the general reserve; 25% is transferred to patronage refund fund. This amount is distributed to the members as per the methodology prescribed in the act. Any amount remaining undistributed by the end of the next fisal year has to be transferred to the General reserve. Similarly, out of the profits for a fiscal year remaining after apportionment to the general reserve; 0.5% is transferred to co-operative promotion fund. This amount has to be deposited into the Poverty Alleviation Fund set-up under the Ministry of Land Management, Co-operatives and Poverty Alleviation.
B17: Out of profits for the year remaining after allocation to general reserve, patronage refund reserve and co-operatives promotion fund; 70% is transferred to share dividend fund and 5% to each of losses recovery fund, cooperatvie education fund, co-operative development fund, community development fund, stabilization fund and other risk management fund.
B18: Particulars | D18: =D7 -> As at 32nd Ashadh 2082 | E18: =E7 -> As at 31st Ashadh 2081 | F18: =F7 -> As at 1st Shrawan 2080
B19: Share Dividend Fund | D19: ='Other Reserve'!C16 -> 1742807.3 | E19: ='Other Reserve'!C11 -> 4795878.7 | F19: ='Other Reserve'!C6 -> 6373002
B20: Losses Recovery Fund | D20: ='Other Reserve'!E16 -> 537214.77 | E20: ='Other Reserve'!E11 -> 507678.18 | F20: ='Other Reserve'!E6 -> 424866.8
B21: Cooperative Education Fund | D21: ='Other Reserve'!D16 -> 757595.27 | E21: ='Other Reserve'!D11 -> 728058.68 | F21: ='Other Reserve'!D6 -> 645247.3
B22: Cooperative Development Fund | D22: ='Other Reserve'!F16 -> 537214.77 | E22: ='Other Reserve'!F11 -> 507678.18 | F22: ='Other Reserve'!F6 -> 424866.8
B23: Community Development Fund | D23: ='Other Reserve'!G16 -> 500714.77 | E23: ='Other Reserve'!G11 -> 507678.18 | F23: ='Other Reserve'!G6 -> 424866.8
B24: Stablization Fund | D24: ='Other Reserve'!H16 -> 29536.588 | E24: ='Other Reserve'!H11 -> 82811.377 | F24: ='Other Reserve'!H6 -> 424866.8
B25: Other Risk Management Fund | D25: ='Other Reserve'!I16 -> 786050.4 | E25: ='Other Reserve'!I11 -> 756513.81 | F25: ='Other Reserve'!I6 -> 673702.43
B26: Total | D26: =SUM(D19:D25) -> 4891133.9 | E26: =SUM(E19:E25) -> 7886297.1 | F26: =SUM(F19:F25) -> 9391418.9 | G26: ='Other Reserve'!J6 -> 9391418.9
B28: 4.20 Contingent liabilities
B29: The cooperative does not have any material contingent liabilities that warrant disclosures
B31: 4.21 Capital commitments
B32: The cooperative does not have any Capital Commitments for this year.

Sheet 4.22-4.33
B1: ='4.18-4.21'!B1 -> ABC Savings and Credit Cooperative Limited
B2: ='4.18-4.21'!B2 -> Notes to Accounts
B3: ='4.18-4.21'!B3 -> For the year ended 32nd Ashadh, 2082
B5: 4.22 Interest Income
B6: Particulars | D6: FY 2081/82 | E6: FY 2080/81
B7: Cash and cash equivalent | D7: 678403.16 | E7: 566920.04
B8: Placement with bank and financial institutions | D8: 908645.42 | E8: 950194.96
B9: Loan and advances to members | D9: 16655832 | E9: =4273716.953+9333000 -> 13606717
B10: Loan and advances to staff | D10: 786258.34 | E10: 615810.14
B11: Other Interest Income | D11: 0 | E11: 0
B12: Total interest income | D12: =SUM(D7:D11) -> 19029139 | E12: =SUM(E7:E11) -> 15739642
B15: 4.23 Interest Expenses
B16: Particulars | D16: =D6 -> FY 2081/82 | E16: =E6 -> FY 2080/81
B17: Borrowings from banks and financial institutions | D17: 800136.19 | E17: 0
B18: Deposits from members | D18: 7018984.9 | E18: 6913198.5
B19: Other | D19: 0 | E19: 0
B20: Total Interest Expenses | D20: =SUM(D17:D19) -> 7819121.1 | E20: =SUM(E17:E19) -> 6913198.5
B23: 4.24 Sales and Other Operating Income
B24: Particulars | D24: =D16 -> FY 2081/82 | E24: =E16 -> FY 2080/81
B25: Sale of merchandise items | D25: 1251559 | E25: 901478.29
B26: Less: Discount on sales | D26: -132520.59 | E26: =-1332014.65/10 -> -133201.46
B27: Net sale of merchandise items | D27: =SUM(D25:D26) -> 1119038.4 | E27: =SUM(E25:E26) -> 768276.83
B28: Other income from lending activities (refer 4.24.1) | D28: =D40 -> 697057.22 | E28: =E40 -> 630627.17
B29: Income from services to members (refer 4.24.2) | D29: =D47 -> 335047.18 | E29: =E47 -> 213053.51
B30: Other income from members (refer 4.24.3) | D30: =D54 -> 88210 | E30: =E54 -> 54100
B31: Total Sales and Other Operating Income | D31: =SUM(D27:D30) -> 2239352.8 | E31: =SUM(E27:E30) -> 1666057.5
B33: 4.24.1 Other income from lending activities
B34: Particulars | D34: =D24 -> FY 2081/82 | E34: =E24 -> FY 2080/81
B35: Loan management fees | D35: 520046.95 | E35: 480105.03
B36: Valuation and related fees | D36: 82000 | E36: 64750
B37: Late fines and penalties on overdue loans | D37: 88610.27 | E37: 77522.133
B38: Late fines and penalties on overdue compulsory deposits | D38: 2050 | E38: 3650
B39: Account closure fees | D39: 4350 | E39: 4600
B40: Total other income from lending activities | D40: =SUM(D35:D39) -> 697057.22 | E40: =SUM(E35:E39) -> 630627.17
B42: 4.24.2 Income from services to members
B43: Particulars | D43: =D34 -> FY 2081/82 | E43: =E34 -> FY 2080/81
B44: Training Income | D44: 76724.801 | E44: 67854.56
B45: Insurance and Remmittence Commission | D45: 79950.5 | E45: 96019
B46: Other Incomes | D46: 178371.88 | E46: 49179.95
B47: Total income from service to members | D47: =SUM(D44:D46) -> 335047.18 | E47: =SUM(E44:E46) -> 213053.51
B50: 4.24.3 Other income from members
B51: Particulars | D51: =D43 -> FY 2081/82 | E51: =E43 -> FY 2080/81
B52: Membership Fees | D52: 76110 | E52: 40000
B53: Fines and penalties related to delayed renewal | D53: 12100 | E53: 14100
B54: Total other income from members | D54: =SUM(D52:D53) -> 88210 | E54: =SUM(E52:E53) -> 54100
B57: 4.25 Cost of Goods Sold and Other Direct Expenses
B58: Particulars | D58: =D51 -> FY 2081/82 | E58: =E51 -> FY 2080/81
B59: Cost of merchadise goods sold (refer 4.25.1) | D59: =D70 -> 268855.73 | E59: =E70 -> 222747.24
B60: Other direct expenses | D60: 0 | E60: 0
B61: Total Cost of Goods Sold and Other Operating Expenses | D61: =SUM(D59:D60) -> 268855.73 | E61: =SUM(E59:E60) -> 222747.24
B64: 4.25.1 Cost of Merchandise Goods Sold
B65: Particulars | D65: =D58 -> FY 2081/82 | E65: =E58 -> FY 2080/81
B66: Opening stock of merchandise | D66: =-E69 -> 253370.89 | E66: 261888.44
B67: Purchases | D67: 223544.8 | E67: 184929.7
B68: Direct expenses | D68: 5200 | E68: 29300
B69: Closing stock of merchandise | D69: -213259.97 | E69: -253370.89
B70: Total Cost of Goods Sold | D70: =SUM(D66:D69) -> 268855.73 | E70: =SUM(E66:E69) -> 222747.24
B73: 4.26 Other Incomes
B74: Particulars | D74: =D65 -> FY 2081/82 | E74: =E65 -> FY 2080/81
B75: Grant income | D75: =-'4.11-4.17'!D108 -> 84059.846 | E75: =-'4.11-4.17'!E108 -> 86115
B76: Fair value gain/loss on investment properties | D76: ='4.6-4.7'!D24 -> 150000 | E76: ='4.6-4.7'!E24 -> 250000
B77: Dividend on equity instruments | D77: 82323.527 | E77: 78680.45
B78: Patronage refund income receipt | D78: 43280.109 | E78: 47172.427
B79: Gain/loss on sale of investment property | D79: 0 | E79: 0
B80: Other | D80: 0 | E80: 0
B81: Total | D81: =SUM(D75:D80) -> 359663.48 | E81: =SUM(E75:E80) -> 461967.88 | F81: =E81-E76 -> 211967.88
B84: 4.27 Impairment charge/(reversal) for loan and other losses
B85: Particulars | D85: =D74 -> FY 2081/82 | E85: =E74 -> FY 2080/81
B86: Impairment charge/(reversal) on loan and advances to members | D86: ='4.1-4.4'!D66+'4.1-4.4'!D67 -> 443793.17 | E86: ='4.1-4.4'!E66+'4.1-4.4'!E67 -> 479480.17
B87: Impairment charge/(reversal) on loan and advances to staff | D87: 0 | E87: 0
B88: Impairment charge/(reversal) on property, plant and equipment | D88: 0 | E88: 0
B89: Impairment charge/(reversal) on goodwill and intangible assets | D89: 0 | E89: 0
B90: Impairment charge/(reversal) on investment properties | D90: 0 | E90: 0
B91: Impairment charge/(reversal) on other receivables | D91: 0 | E91: 0
B92: Total | D92: =SUM(D86:D91) -> 443793.17 | E92: =SUM(E86:E91) -> 479480.17
B95: 4.28 Employment Benefit Expenses
B96: Particulars | D96: =D85 -> FY 2081/82 | E96: =E85 -> FY 2080/81
B97: Short term employee benefit
B98: Salary and allowances | D98: 743116.45 | E98: 687960.09
B99: Uniform | D99: 92500 | E99: 83000
B100: Training & development expenses | D100: 174752.27 | E100: 122922.46
B101: Medical expenses | D101: 55000 | E101: 50000
B102: Insurance premium | D102: 259212.43 | E102: 266007.45
B103: Amortization of prepaid staff expense related to loans at concessional rates | D103: =D10 -> 786258.34 | E103: =E10 -> 615810.14
B104: Employees Bonus | D104: 582507.53 | E104: 411808.73
B105: Defined Contribution Plan
B106: Social Security Fund contribution expense | D106: 192462.84 | E106: 124361.63
B107: Citizen Investment Trust contribution expense | D107: 83220 | E107: 85215.431
B108: Defined Benefit Plan
B109: Gratuity expense | D109: ='4.11-4.17'!E75 -> 689926.22 | E109: ='4.11-4.17'!F75 -> 544364.93
B110: Other Long Term Employee Benefits
B111: Leave encashment | D111: ='4.11-4.17'!E94 -> 99574.167 | E111: ='4.11-4.17'!F94 -> 120333.33
B112: Total personnel expenses | D112: =SUM(D98:D111) -> 3758530.3 | E112: =SUM(E98:E111) -> 3111784.2
B114: 4.29 Other Administrative and Operating Expense
B115: Particulars | D115: =D96 -> FY 2081/82 | E115: =E96 -> FY 2080/81
B116: Board and Sub-Committee Meeting Allowances | D116: 99350 | E116: 92350
B117: Board and Sub-Committee Meeting Expenses | D117: 25500 | E117: 20629.732
B118: Statutory auditors' remuneration | D118: 75000 | E118: 75000
B119: Statutory audit related expenses | D119: 47180 | E119: 33800
B120: Internal audit fee expenses | D120: =E120 -> 100000 | E120: 100000
...

Sheet 5.3
A1: ='4.22-4.33'!B1 -> ABC Savings and Credit Cooperative Limited
A2: ='4.22-4.33'!B2 -> Notes to Accounts
A3: ='4.22-4.33'!B3 -> For the year ended 32nd Ashadh, 2082
A5: 5.3 Classification of financial assets and financial liabilities
A6: The financial assets and liabilities are classified in Amortised Cost, fair value through profit and loss. The following table exhibit the the classification of financial assets and liabilities:
A8: Financial Assets | B8: As on 32nd Asadh 2082
B9: Amortised Cost | C9: FVTPL | D9: Total
A10: Cash and Cash Equivalents | B10: =D10 -> 7642628.6 | C10: 0 | D10: =SoFP!D8 -> 7642628.6
A11: Placement with Bank and Financial Institutions | B11: =D11 -> 10319988 | C11: 0 | D11: =SoFP!D9 -> 10319988
A12: Loans and Advances to Members | B12: =D12 -> 1.2713279e+08 | C12: 0 | D12: =SoFP!D10 -> 1.2713279e+08
A13: Loans and Advances to Staff | B13: =D13 -> 5078018.6 | C13: 0 | D13: =SoFP!D11 -> 5078018.6
A14: Investment Securities | B14: =D14 -> 1211000 | C14: 0 | D14: =SoFP!D12 -> 1211000
A15: Other Assets | B15: =D15 -> 1928060.5 | C15: 0 | D15: ='4.11-4.17'!D9+'4.11-4.17'!D10+'4.11-4.17'!D12 -> 1928060.5
A16: Total Financial Assets | B16: =SUM(B10:B15) -> 1.5331249e+08 | C16: =SUM(C10:C15) -> 0 | D16: =SUM(D10:D15) -> 1.5331249e+08
A18: Financial Liabilities
A19: Deposits from Members | B19: =D19 -> 1.4127537e+08 | C19: 0 | D19: =SoFP!D22 -> 1.4127537e+08
A20: Borrowings | B20: =D20 -> 2305000 | C20: 0 | D20: =SoFP!D23 -> 2305000
A21: Other Liabilities | B21: =D21 -> 0 | C21: 0 | D21: 0
A22: Total Financial Liabilites | B22: =SUM(B19:B21) -> 1.4358037e+08 | C22: =SUM(C19:C21) -> 0 | D22: =SUM(D19:D21) -> 1.4358037e+08
A25: Financial Assets | B25: As on 31st Ashar 2081
B26: Amortised Cost | C26: FVTPL | D26: Total
A27: Cash and Cash Equivalents | B27: =D27 -> 6871672.2 | C27: 0 | D27: =SoFP!E8 -> 6871672.2
A28: Placement with Bank and Financial Institutions | B28: =D28 -> 9375829.9 | C28: 0 | D28: =SoFP!E9 -> 9375829.9
A29: Loans and Advances to Members | B29: =D29 -> 1.2535608e+08 | C29: 0 | D29: =SoFP!E10 -> 1.2535608e+08
A30: Loans and Advances to Staff | B30: =D30 -> 3980298.8 | C30: 0 | D30: =SoFP!E11 -> 3980298.8
A31: Investment Securities | B31: =D31 -> 951000 | C31: 0 | D31: =SoFP!E12 -> 951000
A32: Other Assets | B32: =D32 -> 493386.39 | C32: 0 | D32: ='4.11-4.17'!E9+'4.11-4.17'!E10+'4.11-4.17'!E12 -> 493386.39
A33: Total Financial Assets | B33: =SUM(B27:B32) -> 1.4702827e+08 | C33: =SUM(C27:C32) -> 0 | D33: =SUM(D27:D32) -> 1.4702827e+08
A35: Financial Liabilities
A36: Deposits from Members | B36: =D36 -> 1.344776e+08 | C36: 0 | D36: =SoFP!E22 -> 1.344776e+08
A37: Borrowings | B37: =D37 -> 1312500 | C37: 0 | D37: =SoFP!E23 -> 1312500
A38: Other Liabilities | B38: =D38 -> 0 | C38: 0 | D38: 0
A39: Total Financial Liabilites | B39: =SUM(B36:B38) -> 1.357901e+08 | C39: =SUM(C36:C38) -> 0 | D39: =SUM(D36:D38) -> 1.357901e+08
A42: Financial Assets | B42: As on 1st Shrawan 2080
B43: Amortised Cost | C43: FVTPL | D43: Total
A44: Cash and Cash Equivalents | B44: =D44 -> 6246974.7 | C44: 0 | D44: =SoFP!F8 -> 6246974.7
A45: Placement with Bank and Financial Institutions | B45: =D45 -> 9282999.9 | C45: 0 | D45: =SoFP!F9 -> 9282999.9
A46: Loans and Advances to Members | B46: =D46 -> 1.2327044e+08 | C46: 0 | D46: =SoFP!F10 -> 1.2327044e+08
A47: Loans and Advances to Staff | B47: =D47 -> 3459135.8 | C47: 0 | D47: =SoFP!F11 -> 3459135.8
A48: Investment Securities | B48: =D48 -> 951000 | C48: 0 | D48: =SoFP!F12 -> 951000
A49: Other Assets | B49: =D49 -> 635355.39 | C49: 0 | D49: ='4.11-4.17'!F9+'4.11-4.17'!F10+'4.11-4.17'!F12 -> 635355.39
A50: Total Financial Assets | B50: =SUM(B44:B49) -> 1.4384591e+08 | C50: =SUM(C44:C49) -> 0 | D50: =SUM(D44:D49) -> 1.4384591e+08
A52: Financial Liabilities
A53: Deposits from Members | B53: =D53 -> 1.2985105e+08 | C53: 0 | D53: =SoFP!F22 -> 1.2985105e+08
A54: Borrowings | B54: =D54 -> 1565500 | C54: 0 | D54: =SoFP!F23 -> 1565500
A55: Other Liabilities | B55: =D55 -> 0 | C55: 0 | D55: 0
A56: Total Financial Liabilites | B56: =SUM(B53:B55) -> 1.3141655e+08 | C56: =SUM(C53:C55) -> 0 | D56: =SUM(D53:D55) -> 1.3141655e+08

Sheet 5.7_NFRS1
B1: ='5.3'!A1 -> ABC Savings and Credit Cooperative Limited
B2: ='5.3'!A2 -> Notes to Accounts
B3: ='5.3'!A3 -> For the year ended 32nd Ashadh, 2082
B5: 5.7 First time adoption of NFRS to SMEs
B6: These financial statements, for the year ended 32nd Ashad 2082 are the first, the coopeerative has prepared in accordance with NFRS for SMEs. For periods up to and including the year ended 31st Ashad 2081, the cooperative prepared its financial statements in accordance with local generally accepted accounting principles (Previous GAAP). In preparing these financial statements, the cooperative’s opening statement of financial position was prepared as at 1st Shrawan 2080, the cooperative’s date of transition to NFRS for SMEs. This note explains the principal adjustments made by the cooperative in restating its previous GAAP statements of financial position as at 1st Shrawan 2080 and its previously published previous GAAP financial statements as at and for the year ended 31st Ashad 2081.
B7: Exemptions applied Section 35 Transition to NFRS for SMEs Standards allows first-time adopters certain exemptions from the retrospective application of certain standard. The cooperative has applied the following exemptions: a) Estimates On the assessment of estimates made under the previous GAAP financial statements, the cooperative has concluded that there is no necessity to revise the estimate under NFRS for SMEs, as there is no objective evidence that those estimates were in error. However, estimates that were required under NFRS for SMEs but not required under previous GAAP are made by the cooperative for the relevant reporting dates reflecting conditions existing as at that date. b) Deemed cost: The cooperative has used revaluation as deemed cost for land and investment properties at the date of transition as its deemed cost. The cooperative has used carrying amounts as per previous GAAP as deemed cost for other assets since those values were broadly comparable to fair values.
B8: Transition to NFRS for SMEs –Reconciliation The following reconciliations provide the explanations and quantification of the differences arising from the transition from previous GAAP to NFRS for SMEs in accordance with section 35. I. Reconciliation of equity as at 1st Shrawan 2080. II. Reconciliation of equity as at 31st Ashadh 2081. III. Reconciliation of statement of comprehensive income for the year ended 31st Ashadh 2081. IV. Reconciliation of statement of cashflows for the year ended 31st Ashadh 2081. Previous GAAP information has been reclassified/regrouped in accordance with NFRS for SMEs, wherever necessary, based on the audited financial statement of the cooperation for the year ended 31st Ashad 2080 and 31st Ashad 2081.
B10: 5.7.1 First time adoption of NFRS for SMEs
B11: I. Reconciliation of equity as at 1st Shrawan 2080 (date of transition to NFRS for SMEs) | F11: Figures in NPR
C12: E.N. * | D12: Previous GAAP | E12: Adjustments | F12: NFRS balance
B14: Assets
B15: Cash and Cash Equivalents | C15: 1 | D15: 1321974.9 | E15: =F15-D15 -> 4924999.8 | F15: =SoFP!F8 -> 6246974.7
B16: Placement with Bank and Financial Institutions | C16: 1 | D16: 0 | E16: =F16-D16 -> 9282999.9 | F16: =SoFP!F9 -> 9282999.9
B17: Loans and Advances to Members | C17: 2 | D17: 1.5006376e+08 | E17: =F17-D17 -> -26793318 | F17: =SoFP!F10 -> 1.2327044e+08 | G17: =F17-EN_SoFP!C20 -> 0
B18: Loans and Advances to Staff | C18: 3 | D18: 0 | E18: =F18-D18 -> 3459135.8 | F18: =SoFP!F11 -> 3459135.8 | G18: =F17-EN_SoFP!C20 -> 0
B19: Investment Securities | C19: 4 | D19: 15159000 | E19: =F19-D19 -> -14208000 | F19: =SoFP!F12 -> 951000
B20: Current Tax Assets | C20: 5 | D20: 0 | E20: =F20-D20 -> 706629.3 | F20: =SoFP!F13 -> 706629.3
B21: Investment Property | C21: 6 | D21: 0 | E21: =F21-D21 -> 934450 | F21: =SoFP!F14 -> 934450
B22: Property and Equipment | C22: 7 | D22: 17755675 | E22: =F22-D22 -> 2719787.8 | F22: =SoFP!F15 -> 20475463
B23: Goodwill and Intangible Assets | C23: 7 | D23: 0 | E23: =F23-D23 -> 693769.8 | F23: =SoFP!F16 -> 693769.8
B24: Other Assets | C24: 9 | D24: 3244500.2 | E24: =F24-D24 -> -406237.96 | F24: =SoFP!F17 -> 2838262.3 | G24: =F24-EN_SoFP!C85 -> 0
B25: Total Assets | D25: =SUM(D15:D24) -> 1.8754491e+08 | E25: =SUM(E15:E24) -> -18685783 | F25: =SUM(F15:F24) -> 1.6885913e+08
B27: Particulars
B28: Liabilities
B29: Deposits from Members | D29: 1.2985105e+08 | E29: =F29-D29 -> 6.7859888e-05 | F29: =SoFP!F22 -> 1.2985105e+08
B30: Borrowings | C30: 10 | D30: 0 | E30: =F30-D30 -> 1565500 | F30: =SoFP!F23 -> 1565500
B31: Current Tax Liabilities | C31: 5 | D31: 347296.28 | E31: =F31-D31 -> -347296.28 | F31: 0
B32: Provision for Employee Benefits | C32: 11 | D32: 0 | E32: =F32-D32 -> 2113505.1 | F32: =SoFP!F24 -> 2113505.1
B33: Deferred Tax Liabilities | C33: 8 | D33: 0 | E33: =F33-D33 -> 1064561.5 | F33: =SoFP!F25 -> 1064561.5
B34: Loan Loss Provision | C34: 2 | D34: 22052044 | E34: =F34-D34 -> -22052044
B35: Grant Liabilities | C35: 12 | D35: 362425.61 | E35: =F35-D35 -> 615115 | F35: =SoFP!F26 -> 977540.61
B36: Other Liabilities | C36: 13 | D36: 3759628.8 | E36: =F36-D36 -> -1778591.9 | F36: =SoFP!F27 -> 1981037
B37: Total Liabilities | D37: =SUM(D29:D36) -> 1.5637245e+08 | E37: =SUM(E29:E36) -> -18819251 | F37: =SUM(F29:F36) -> 1.375532e+08
B38: Equity
B39: Share Capital | D39: 13732000 | E39: =F39-D39 -> 0 | F39: =SoFP!F30 -> 13732000
B40: General Reserve Fund | D40: 7076728.8 | E40: =F40-D40 -> 0 | F40: =SoFP!F31 -> 7076728.8
B41: Patronage Refund Reserve | D41: 570291.02 | E41: =F41-D41 -> 0 | F41: =SoFP!F32 -> 570291.02
B42: Other Statutory Reserves | D42: 9391418.9 | E42: =F42-D42 -> 0 | F42: =SoFP!F33 -> 9391418.9
B43: Revaluation Reserve | C43: 14 | D43: 0 | E43: =F43-D43 -> 2730846.1 | F43: =SoFP!F34 -> 2730846.1
B44: Retained Earnings | C44: 15 | D44: 0 | E44: =F44-D44 -> -2495355.1 | F44: =SoFP!F36 -> -2495355.1
B45: Fair Value Reserve | C45: 16 | D45: 0 | E45: =F45-D45 -> 300000 | F45: =SoFP!F35 -> 300000
B46: Other Reserves and Funds | C46: 17 | D46: 402023.11 | E46: =F46-D46 -> -402023.11 | F46: 0
B47: Total Equity | D47: =SUM(D39:D46) -> 31172462 | E47: =SUM(E39:E46) -> 133467.82 | F47: =SUM(F39:F46) -> 31305930
B48: Total Liabilities and Equity | D48: =D47+D37 -> 1.8754491e+08 | E48: =E47+E37 -> -18685783 | F48: =F47+F37 -> 1.6885913e+08
B49: *E.N.: Explanatory Note
B51: 5.7.2 First time adoption of NFRS for SMEs (continued)
B52: II. Reconciliation of equity as at 31st Ashad 2081
C53: E.N. | D53: =D12 -> Previous GAAP | E53: Adjustments | F53: NFRS balance
B55: Assets
B56: Cash and Cash Equivalents | C56: 1 | D56: 1454172.3 | E56: =F56-D56 -> 5417499.8 | F56: =SoFP!E8 -> 6871672.2
B57: Placement with Bank and Financial Institutions | C57: 1 | D57: 0 | E57: =F57-D57 -> 9375829.9 | F57: =SoFP!E9 -> 9375829.9
B58: Loans and Advances to Members | C58: 2 | D58: 1.534004e+08 | E58: =F58-D58 -> -28044323 | F58: =SoFP!E10 -> 1.2535608e+08
B59: Loans and Advances to Staff | C59: 3 | D59: 0 | E59: =F59-D59 -> 3980298.8 | F59: =SoFP!E11 -> 3980298.8
B60: Investment Securities | C60: 4 | D60: 15744330 | E60: =F60-D60 -> -14793330 | F60: =SoFP!E12 -> 951000
B61: Current Tax Assets | C61: 5 | D61: 0 | E61: =F61-D61 -> 842646.05 | F61: =SoFP!E13 -> 842646.05
B62: Investment Property | C62: 6 | D62: 0 | E62: =F62-D62 -> 1984450 | F62: =SoFP!E14 -> 1984450
B63: Property and Equipment | C63: 7 | D63: 18679073 | E63: =F63-D63 -> 2637701.8 | F63: =SoFP!E15 -> 21316775
B64: Goodwill and Intangible Assets | C64: 7 | D64: 0 | E64: =F64-D64 -> 775855.79 | F64: =SoFP!E16 -> 775855.79
B65: Other Assets | C65: 9 | D65: 4543749.5 | E65: =F65-D65 -> -1533292.3 | F65: =SoFP!E17 -> 3010457.2 | G65: =F65-EN_SoFP!D85 -> 0
B66: Total Assets | D66: =SUM(D56:D65) -> 1.9382173e+08 | E66: =SUM(E56:E65) -> -19356663 | F66: =SUM(F56:F65) -> 1.7446507e+08
B68: Particulars
B69: Liabilities
B70: Deposits from Members | D70: 1.344776e+08 | E70: =F70-D70 -> -0.0037495196 | F70: =SoFP!E22 -> 1.344776e+08
B71: Borrowings | C71: 10 | D71: 0 | E71: =F71-D71 -> 1312500 | F71: =SoFP!E23 -> 1312500
B72: Current Tax Liabilities | C72: 5 | D72: 788696.18 | E72: =F72-D72 -> -788696.18 | F72: 0
B73: Provision for Employee Benefits | C73: 11 | D73: 0 | E73: =F73-D73 -> 2496203.4 | F73: =SoFP!E24 -> 2496203.4
B74: Deferred Tax Liabilities | C74: 8 | D74: 0 | E74: =F74-D74 -> 364141.49 | F74: =SoFP!E25 -> 364141.49
B75: Loan Loss Provision | C75: 2 | D75: 22531525 | E75: =F75-D75 -> -22531525 | F75: 0
B76: Grant Liabilities | C76: 12 | D76: 100000 | E76: =F76-D76 -> 529000 | F76: =SoFP!E26 -> 629000
B77: Other Liabilities | C77: 13 | D77: 3419154.9 | E77: =F77-D77 -> -1418575.7 | F77: =SoFP!E27 -> 2000579.2
B78: Total Liabilities | D78: =SUM(D70:D77) -> 1.6131697e+08 | E78: =SUM(E70:E77) -> -20036952 | F78: =SUM(F70:F77) -> 1.4128002e+08
B79: Equity
B80: Share Capital | D80: 15686000 | E80: =F80-D80 -> 0 | F80: =SoFP!E30 -> 15686000
B81: General Reserve Fund | D81: 7953754.8 | E81: =F81-D81 -> 0 | F81: =SoFP!E31 -> 7953754.8
B82: Patronage Refund Reserve | D82: 555781.05 | E82: =F82-D82 -> 0 | F82: =SoFP!E32 -> 555781.05
B83: Other Statutory Reserves | D83: 7886297.1 | E83: =F83-D83 -> 0 | F83: =SoFP!E33 -> 7886297.1
B84: Revaluation Reserve | C84: 14 | D84: 0 | E84: =F84-D84 -> 2730846.1 | F84: =SoFP!E34 -> 2730846.1
B85: Retained Earnings | C85: 15 | D85: 0 | E85: =F85-D85 -> -2177633.3 | F85: =SoFP!E36 -> -2177633.3
B86: Fair Value Reserve | C86: 16 | D86: 0 | E86: =F86-D86 -> 550000 | F86: =SoFP!E35 -> 550000
B87: Other Reserves and Funds | C87: 17 | D87: 422924.35 | E87: =F87-D87 -> -422924.35 | F87: 0
B88: Total Equity | D88: =SUM(D80:D87) -> 32504757 | E88: =SUM(E80:E87) -> 680288.39 | F88: =SUM(F80:F87) -> 33185046
B89: Total Liabilities and Equity | D89: =D88+D78 -> 1.9382173e+08 | E89: =E88+E78 -> -19356663 | F89: =F88+F78 -> 1.7446507e+08
B92: 5.4.3 First time adoption of NFRS for SMEs (continued)
B93: III. Reconciliation of total comprehensive income for the year ended 31st Ashad 2081
C95: E.N. | D95: Previous GAAP | E95: Adjustments | F95: NFRS balance
B96: Interest Income | C96: 18 | D96: 15123832 | E96: =F96-D96 -> 615810.14 | F96: =SoPL!E8 -> 15739642
B97: Interest Expense | D97: =F97 -> -6913198.5 | E97: =F97-D97 -> 0 | F97: =SoPL!E9 -> -6913198.5
B98: Net Interest Income | D98: =SUM(D96:D97) -> 8210633.5 | E98: =F98-D98 -> 615810.14 | F98: =SUM(F96:F97) -> 8826443.6
B99: Sales and Other Operating Income | C99: 19 | D99: =EN_SoCI_SoCF!D16 -> 1443310.3 | E99: =F99-D99 -> 222747.24 | F99: =SoPL!E11 -> 1666057.5
B100: Cost of Goods Sold and Other Direct Expenses | C100: 20 | D100: 0 | E100: =F100-D100 -> -222747.24 | F100: =SoPL!E12 -> -222747.24
B101: Net Sales and Other Operating Income | D101: =SUM(D99:D100) -> 1443310.3 | E101: =F101-D101 -> 3.0267984e-09 | F101: =SoPL!E13 -> 1443310.3
B102: Net Interest, Fee and Commisson Income | D102: =D101+D98 -> 9653943.7 | E102: =F102-D102 -> 615810.14 | F102: =SoPL!E14 -> 10269754
B103: Net Trading Income | D103: 0 | E103: =F103-D103 -> 0 | F103: 0
B104: Other Incomes | C104: 21 | D104: 211967.88 | E104: =F104-D104 -> 250000 | F104: =SoPL!E15 -> 461967.88
B105: Total Operating Income | D105: =D104+D102 -> 9865911.6 | E105: =F105-D105 -> 865810.14 | F105: =SoPL!E16 -> 10731722
B106: Impairment (Charge)/ Reversal for Loans and Other Losses | D106: =F106 -> -479480.17 | E106: =F106-D106 -> 0 | F106: =SoPL!E17 -> -479480.17
B107: Net Operating Income | D107: =SUM(D105:D106) -> 9386431.4 | E107: =F107-D107 -> 865810.14 | F107: =SoPL!E18 -> 10252242
B108: Operating Expense | E108: =F108-D108 -> 0
B109: Employee Benefit Expenses | C109: 22 | D109: -1578544.6 | E109: =F109-D109 -> -1533239.6 | F109: =SoPL!E20 -> -3111784.2
B110: Other Administrative and Operating Expenses | C110: 23 | D110: =-2492177.19733333 -> -2492177.2 | E110: =F110-D110 -> 183102.74 | F110: =SoPL!E21 -> -2309074.5
...

Sheet EN_SoFP
A1: ='5.7_NFRS1'!B1 -> ABC Savings and Credit Cooperative Limited
A2: Explanatory Notes Related to Equity and the Statement of Financial Position
A3: ='5.7_NFRS1'!B3 -> For the year ended 32nd Ashadh, 2082
A5: EN-1: Cash and Cash Equivalents
A6: Under GAAP, fixed term deposits with banks had been classified as "investments". Under NFRS for SMEs, fixed term depsoits with original maturity upto 3 months have been reclassified under "cash and cash equivalents" and those of longer maturity have been classified under "Placement with banks and financial institutions".
A7: Particulars | C7: 1 Shrawan 2080 | D7: 31 Ashadh 2081
A8: Cash and Cash Equivalents as per GAAP | C8: ='5.7_NFRS1'!D15 -> 1321974.9 | D8: ='5.7_NFRS1'!D56 -> 1454172.3
A9: Add: Fixed term deposits with original maturity upto 3 months | C9: ='4.1-4.4'!F12 -> 4924999.8 | D9: ='4.1-4.4'!E12 -> 5417499.8
A10: Cash and Cash Equivalents as per NFRS for SMEs | C10: =SUM(C8:C9) -> 6246974.7 | D10: =SUM(D8:D9) -> 6871672.2
A11: Fixed term deposits with original maturity more than 3 months (classified as placement with banks and financial institutions) | C11: ='4.1-4.4'!F23 -> 9282999.9 | D11: ='4.1-4.4'!E23 -> 9375829.9
A14: EN-2: Loans and Advances to Members
A15: Under GAAP, loans to employees had been classified under "Loan and advance investments". Loans to staff have now been presented as a separate line item in the statement of financial position. Moreover, the provision for impairment on loans (referred to as loan loss provision under GAAP) had been presented as a liability under GAAP. The provision has now been netted-off against the gross carrying amount of loans and advances.
A16: Particulars | C16: 1 Shrawan 2080 | D16: 31 Ashadh 2081
A17: Loans and advances as per GAAP | C17: ='5.7_NFRS1'!D17 -> 1.5006376e+08 | D17: ='5.7_NFRS1'!D58 -> 1.534004e+08
A18: Less: Loans to staff | C18: =-'4.1-4.4'!F111 -> -4741273.4 | D18: =-'4.1-4.4'!E111 -> -5512798.7
A19: Less: Provision for impairment of loans and advances | C19: =-'4.1-4.4'!$F$85 -> -22052044 | D19: =-'4.1-4.4'!$E$85 -> -22531525
A20: Loans and Advances to Member as per NFRS for SMEs | C20: =SUM(C17:C19) -> 1.2327044e+08 | D20: =SUM(D17:D19) -> 1.2535608e+08
A23: EN-3: Loans and Advances to Staff
A24: Under GAAP; loans to staff at concessional rates of interest were measured at cost; the actual amounts disbursed less repayments. Under NFRS for SMEs ; these loans have been measured at fair values. Under GAAP, such loans had been classified under "Loan and advance investments". Loans to staff have now been presented as a separate line item in the statement of financial position.
A26: Particulars | C26: 1 Shrawan 2080 | D26: 31 Ashadh 2081
A27: Loans to staff at cost (amounts disbursed less repayments) | C27: ='4.1-4.4'!F111 -> 4741273.4 | D27: ='4.1-4.4'!E111 -> 5512798.7
A28: Less: Fair Value Adjustment | C28: ='4.1-4.4'!F112 -> -1282137.6 | D28: ='4.1-4.4'!E112 -> -1532500
A29: TOTAL | C29: =SUM(C27:C28) -> 3459135.8 | D29: =SUM(D27:D28) -> 3980298.8
A30: Fair Value adjustments of staff loans have been recognized as "Deferred Employee Expenditure" and presented under "Other Assets" (Note 4.11)
A33: EN-4: Investment Securities
A34: Under GAAP, fixed term deposits with banks had been classified as "investments". Under NFRS for SMEs, fixed term depsoits with original maturity upto 3 months have been reclassified under "cash and cash equivalents" and those of longer maturity have been classified under "Placement with banks and financial institutions".
A35: Particulars | C35: 1 Shrawan 2080 | D35: 31 Ashadh 2081
A36: Investment securities as per GAAP | C36: ='5.7_NFRS1'!D19 -> 15159000 | D36: ='5.7_NFRS1'!D60 -> 15744330
A37: Less: Fixed term deposits with original maturity upto 3 months (reclassified to cash and cash equivalents) | C37: =-C9 -> -4924999.8 | D37: =-D9 -> -5417499.8
A38: Less: Fixed term deposits with original maturity more than 3 months (classified to placement with banks and financial institutions) | C38: =-C11 -> -9282999.9 | D38: =-D11 -> -9375829.9
A39: Investment securities as per NFRS for SMEs | C39: =SUM(C36:C38) -> 951000 | D39: =SUM(D36:D38) -> 951000
A42: EN-5: Current tax assets
A43: Under GAAP; current tax liabilities were presented as a separate line item in the statement of financial position and advance payments of income tax were presented under "Other Assets". Under NFRS for SMEs; advance payments of tax and current tax liabilities have been netted-off and presented as net "Current tax assets" or "Current tax liabilities".
A44: Particulars | C44: 1 Shrawan 2080 | D44: 31 Ashadh 2081
A45: Current tax liabilities | C45: =-'4.6-4.7'!F12 -> -347296.28 | D45: =-'4.6-4.7'!E12 -> -788696.18
A46: Current tax assets | C46: =SUM('4.6-4.7'!F8:F9) -> 1053925.6 | D46: =SUM('4.6-4.7'!E8:E9) -> 1631342.2
A47: Current tax assets/ (liabilities) | C47: =SUM(C45:C46) -> 706629.3 | D47: =SUM(D45:D46) -> 842646.05
A49: EN-6: Investment Properties
A50: Under GAAP; non-banking assets; which are land and/or building previously held as collateral against loans and whose ownership was assumed by the cooperative due to inability to realize the properties through auction for recovery of the underlying loans; were presented under "Other Assets". Under NFRS for SMEs; these properties have been reclassified to "Investment Properties" measured at fair value and presented as a separate line item in the statement of financial position.
A51: Particulars | C51: =C44 -> 1 Shrawan 2080 | D51: =D44 -> 31 Ashadh 2081
A52: Non-banking assets as per GAAP | C52: ='4.6-4.7'!$F$22 -> 634450 | D52: =-D83 -> 1434450
A53: Add: Adjustment for fair value | C53: ='4.6-4.7'!$F$24 -> 300000 | D53: ='4.6-4.7'!$E$24+C53 -> 550000
A54: Investment properties as per NFRS for SMEs (reclassified) | C54: =SUM(C52:C53) -> 934450 | D54: =SUM(D52:D53) -> 1984450
A57: EN-7: Property, Plant and Equipment and Goodwill & Intangible Assets
A58: Under GAAP; intangible assets and property, plant and equipment had been grouped under "Fixed Assets". They have now been presented as separate line items in the statement of financial position.
A59: Moreover, land owned by the cooperative have been measured at fair values at the date of transition. Such revaluation has led to increase in the carrying amount of land by 3,413,558.
A60: Particulars | C60: =C51 -> 1 Shrawan 2080 | D60: =D51 -> 31 Ashadh 2081
A61: Fixed assets as per GAAP | C61: ='5.7_NFRS1'!D22 -> 17755675 | D61: ='5.7_NFRS1'!D63 -> 18679073
A62: Less: Intangible Assets | C62: =-'5.7_NFRS1'!F23 -> -693769.8 | D62: =-'5.7_NFRS1'!F64 -> -775855.79
A63: Property, plant and equipment as per GAAP | C63: =SUM(C61:C62) -> 17061905 | D63: =SUM(D61:D62) -> 17903217
A64: Add: Revaluation gain on land | C64: =D64 -> 3413557.6 | D64: ='4.8'!C10 -> 3413557.6
A65: Property, plant and equipment as per NFRS for SMEs | C65: =SUM(C63:C64) -> 20475463 | D65: =SUM(D63:D64) -> 21316775
A68: EN-8: Deferred Tax Assets/(Liabilities)
A69: Remeasurements of property, plant and equipment, defined benefit obligations, other long-term employee benefits have resulted in differences in temporary differences measures as per GAAP and those measured as per NFRS for SMEs. The resulting differences in deferred taxes have been transferred to equity. Details are as follows:
A71: Particulars | C71: =C60 -> 1 Shrawan 2080 | D71: =D60 -> 31 Ashadh 2081
A72: Deferred tax assets/(liabilities) as per GAAP | C72: 0 | D72: 0
A73: Effect of remeasurements on transition to NFRS for SMEs | C73: ='4.10'!K74 -> -1064561.5 | D73: =C73 -> -1064561.5
A74: Less: Effects due to change in temporary differences for FY 2080-81 recognized in statement of profit or loss. | C74: 0 | D74: ='4.10'!K51+C72-D72 -> 700420.06
A75: Cumulative effect on transition to NFRS for SMEs | C75: =SUM(C73:C74) -> -1064561.5 | D75: =SUM(D73:D74) -> -364141.49
A76: Deferred tax assets/ (liabilities) as per NFRS for SMEs | C76: =SUM(C75+C72) -> -1064561.5 | D76: =D72+D75 -> -364141.49
A78: EN-9: Other assets
A79: Various remeasurements and reclassifications upon transition to NFRS for SMEs have resulted in differences in "Other Assets" as per NFRS for SMEs as compared to GAAP. The details are as follows:
A80: Particulars | C80: =C71 -> 1 Shrawan 2080 | D80: =D71 -> 31 Ashadh 2081
A81: Other Assets as per GAAP | C81: ='5.7_NFRS1'!D24 -> 3244500.2 | D81: ='5.7_NFRS1'!D65 -> 4543749.5
A82: Less: Advance payment of income tax reclassified (refer EN-5) | C82: =-C46 -> -1053925.6 | D82: =-D46 -> -1631342.2
A83: Less: Non-banking assets reclassified (refer EN-6) | C83: =-C52 -> -634450 | D83: =-'4.6-4.7'!F22-'4.6-4.7'!E23 -> -1434450
A84: Add: Prepaid expense related to staff loans (refer EN-3) | C84: =-C28 -> 1282137.6 | D84: =-D28 -> 1532500
A85: Other Assets as per NFRS for SMEs | C85: =SUM(C81:C84) -> 2838262.3 | D85: =SUM(D81:D84) -> 3010457.2
A87: EN-10: Borrowings
A88: Under GAAP, loan from NEFSCUN had been grouped under "Current liabilities". The loan has now been presented as a separate line item in the statement of financial position.
A89: Particulars | C89: =C80 -> 1 Shrawan 2080 | D89: =D80 -> 31 Ashadh 2081
A90: Borrowings as per GAAP | C90: 0 | D90: 0
A91: Add: Loan from NEFSCUN | C91: ='4.11-4.17'!F42 -> 1565500 | D91: ='4.11-4.17'!E42 -> 1312500
A92: Borrowings as per NFRS for SMEs | C92: =SUM(C90:C91) -> 1565500 | D92: =SUM(D90:D91) -> 1312500
A94: EN-11: Provision for Employee Benefits
A95: Defined Benefit Obligations
A96: Under GAAP, defined benefit expenses were recognized as expense only upon payment. Upon transition to NFRS for SMEs, they have been recognized as liabilities.
A97: Cooperative assumes that it is not fesiable to use the projected unit credit method to measure its obligation, obligations have been remeasured using simplified approach by ignoring future uncertainties as required by Section 28.19 of Employee Benefits and the resulting differences have been charged against the retained earnings. Details are as follows:
A98: Particulars | C98: =C89 -> 1 Shrawan 2080 | D98: =D89 -> 31 Ashadh 2081
A99: Defined Benefit obligations as per GAAP | C99: 0 | D99: 0
A100: Effect of restatements as at the date of transition | C100: ='4.11-4.17'!F53 -> 1709605.1 | D100: =C100 -> 1709605.1
A101: Changes in expenses charged to profit or loss during FY 2080-81. | C101: 0 | D101: ='4.11-4.17'!F75 -> 544364.93
A102: Payment made during the year ( reocgnised as expenses under GAAP) | D102: -257000
A103: Defined Benefit obligations as per NFRS for SMEs | C103: =SUM(C99:C102) -> 1709605.1 | D103: =SUM(D99:D102) -> 1996970
A105: Other Long-Term Employee Benefit Obligations
A106: Under GAAP, other long-term employee benefit obligations related to home leave and sick leave were recognized as expense only upon payment. Upon transition to NFRS for SMEs, they have been recognized as liabilities.
A107: Cooperative assumes that it is not fesiable to use the projected unit credit method to measure its obligation, obligations have been remeasured using simplified approach by ignoring future uncertainties as required by Section 28.19 of Employee Benefits and the resulting differences have been charged against the retained earnings. Details are as follows:
A108: Particulars | C108: =C98 -> 1 Shrawan 2080 | D108: =D98 -> 31 Ashadh 2081
A109: Other Long-term employee benefit obligations as per GAAP | C109: 0 | D109: 0
A110: Effect of restatements as at the date of transition | C110: ='4.11-4.17'!F54 -> 403900 | D110: =C110 -> 403900
A111: Payment made during the year (reocgnised as expenses under GAAP) | D111: ='4.11-4.17'!$F$95 -> -25000
A112: Changes in expenses charged to profit or loss during FY 2080-81. | D112: 120333.33
A113: Other Long-term employee benefit obligations as per NFRS for SMEs | C113: =SUM(C109:C112) -> 403900 | D113: =SUM(D109:D112) -> 499233.33
A115: Total Provision for Employee Benefits
A116: Particulars | C116: =C108 -> 1 Shrawan 2080 | D116: =D108 -> 31 Ashadh 2081
A117: Total Provision for employee benefits as per GAAP | C117: =C99+C109 -> 0 | D117: =D99+D109 -> 0
A118: Effect of restatements as at the date of transition | C118: =C100+C110 -> 2113505.1 | D118: =D100+D110 -> 2113505.1
A119: Payment made during the year (reocgnise in expesnses in the GAAP) | D119: =D111+D102 -> -282000
A120: Changes in expenses charged to profit or loss during FY 2080-81. | C120: =C101+C112 -> 0 | D120: =D101+D112 -> 664698.26
A121: Total Provision for employee benefits as per NFRS for SMEs | C121: =SUM(C117:C120) -> 2113505.1 | D121: =SUM(D117:D120) -> 2496203.4
...

Sheet EN_SoCI_SoCF
A1: =EN_SoFP!A1 -> ABC Savings and Credit Cooperative Limited
A2: Explanatory Notes Related to Total Comprehensive Income for FY 2080-81
A3: =EN_SoFP!A3 -> For the year ended 32nd Ashadh, 2082
A5: EN-18: Interest Income
A6: Under GAAP; loans to staff were measured at cost; the actual amounts disbursed less repayments. Under NFRS for SMEs; these loans have been measured at fair values. Accordingly, the amortized portions of such staff costs have been recognized as expenses under "Personnel Expenses" with corresponding effect to interest income.
A7: Particulars | D7: FY 2080-81
A8: Interest income as per GAAP | D8: ='5.7_NFRS1'!D96 -> 15123832
A9: Add: Additional Interest income on staff loans recognized at market rates. | D9: ='4.22-4.33'!E103 -> 615810.14
A10: Interest income as per NFRS for SMEs | D10: =SUM(D8:D9) -> 15739642
A13: EN-19: Sales and Other Operating Income
A14: Cost of merchandise items sold had been netted off against related income under GAAP. The expenses have now been presented under a separate heading "Cost of Goods Sold and Other Direct Expenses" under NFRS for SMEs.
A15: Particulars | D15: =D7 -> FY 2080-81
A16: Sales and other operating income as per GAAP | D16: 1443310.3
A17: Add: Cost of merchadise items sold netted-off against income under GAAP | D17: ='4.22-4.33'!E59 -> 222747.24
A18: Sales and other operating income as per NFRS for SMEs | D18: =SUM(D16:D17) -> 1666057.5
A21: EN-20: Cost of Goods Sold and Other Direct Expenses
A22: Various remeasurements and reclassfication under NFRS for SMEs have resulted in differences in "cost of goods sold and other direct expenses" under NFRS for SMEs as compared to GAAP. The details are as follows:
A23: Particulars | D23: =D15 -> FY 2080-81
A24: Cost of Goods Sold and Other Direct Expenses as per GAAP | D24: 0
A25: Add: Cost of merchandise items sold netted-off against income under GAAP (refer EN-19) | D25: =D17 -> 222747.24
A26: Add: Direct expenses related to income from various programmes classified under "Administrative and Operating expenses" under GAAP | D26: =SUM('4.22-4.33'!E60:E60) -> 0
A27: Cost of Goods Sold and Other Direct Expenses as per NFRS for SMEs | D27: =SUM(D24:D26) -> 222747.24
A29: EN-21: other income
A30: Under GAAP; non banking assets is measured at cost. Under NFRS for SMEs; these non banking assets are classifed as investment properties and measure at fair value with differences recognized in profit or loss.
A31: Particulars | D31: =D23 -> FY 2080-81
A32: Other income as per GAAP | D32: ='5.7_NFRS1'!D104 -> 211967.88
A33: Add: Fair value measurement (refer EN-16) | D33: =EN_SoFP!D167-EN_SoFP!C167 -> 250000
A34: Other Income as per NFRS for SMEs | D34: =SUM(D32:D33) -> 461967.88
A36: EN-22: Employment Benefit Expenses
A37: Various remeasurements and reclassfication under NFRS for SMEs have resulted in differences in employment benefit expenses under NFRS for SMEs as compared to GAAP. The details are as follows:
A38: Particulars | D38: =D23 -> FY 2080-81
A39: Personnel expenses as per GAAP | D39: =-'5.7_NFRS1'!D109 -> 1578544.6
A40: Remeasurement of defined benefit obligation expenses and other long-term employee benefit expenses (refer EN-11) | D40: =SUM(EN_SoFP!D119:D120) -> 382698.26
A41: Staff expense related to amortization of fair value adjustment of staff loans at concessional rates of interest | D41: =D9 -> 615810.14
A42: Expenses related to training of staff classified under "administrative and operating expenses" as per GAAP. | D42: ='4.22-4.33'!E100 -> 122922.46
A43: Staff bonus expense presented as a separate line item under GAAP | D43: ='4.22-4.33'!E104 -> 411808.73
A44: Employment Benefit expenses as per NFRS for SMEs | D44: =SUM(D39:D43) -> 3111784.2
A46: EN-23: Other Administrative and Operating Expenses
A47: Various remeasurements and reclassfication under NFRS for SMEs have resulted in differences in personnel expenses under NFRS for SMEs as compared to GAAP. The details are as follows:
A48: Particulars | D48: =D38 -> FY 2080-81
A49: Other administrative and operating expenses as per GAAP | D49: =-'5.7_NFRS1'!D110 -> 2492177.2
A50: Less: Staff training expenses reclassified to "Employement Benefit expenses" (refer EN-22) | D50: =-D42 -> -122922.46
A51: Add: Direct expenses related to income from various programmes reclassified to "cost of goods sold and other direct expenses" | D51: =-D26 -> 0
A52: Less: Loss on sales of Property, Plant and Equipment has been reclassified to the "non operating expenses" | D52: -60180
A53: Other administrative and operating expenses as per NFRS for SMEs | D53: =SUM(D49:D52) -> 2309074.7
A55: EN-24: Non Operating Expenses
A56: Various remeasurements and reclassfication under NFRS for SMEs have resulted in differences in other adminstrative and operating expenses under NFRS for SMEs as compared to GAAP. The details are as follows:
A57: Particulars | D57: =D48 -> FY 2080-81
A58: Loss on sales of Property, Plant and Equipment has been reclassified in the "non operating expenses".( refer EN-23) | D58: =-D52 -> 60180
A59: Other administrative and operating expenses as per NAS for Mes | D59: =SUM(D58:D58) -> 60180
A61: EN-25: Deferred tax expense
A62: Various remeasurements of temporary differences under NFRS for SMEs have resulted in differences in deferred tax income under NFRS for SMEs as compared to GAAP. The details are as follows:
A63: Particulars | D63: =D48 -> FY 2080-81
A64: Deferred tax income/(expense) as per GAAP | D64: ='5.7_NFRS1'!D119 -> 0
A65: Less: Effects due to change in temporary differences for FY 2080-81 recognized in statement of profit or loss. (refer EN-9) | D65: =EN_SoFP!D74 -> 700420.06
A66: Deferred tax income/(expense) as per NFRS for SMEs | D66: =SUM(D64:D65) -> 700420.06
A68: Explanatory Notes Related to Statement of Cash Flows for FY 2080-81 (5.7.4 above)
A70: EN-26
A71: The changes in net cash flows from operating activities, investing activities and financing activities is due to regrouping and reclassification of items required under NFRS for SMEs which are different as compared to the regulatory requirements as per GAAP.
A73: EN-27
A74: The changes in cash and cash equivalents at the end of the period is due to regrouping and reclassification of fixed term deposits of original maturity upto 3 months under "cash and cash equivalents" (refer EN-1)

Sheet Sheet1

Sheet Tax
A2: Profit as per Books | B2: =SoPL!C26 -> 0 | C2: =SoPL!D26 -> 5242567.8
A3: Add: gratuity as per books | C3: ='4.22-4.33'!D109 -> 689926.22 | D3: ='4.22-4.33'!E109 -> 544364.93 | F3: Expenses as per NFRS | I3: =SoPL!E20 -> -3111784.2
A4: Less: Payments made | C4: 0 | F4: Add: provision for gratuity | I4: =C3 -> 689926.22
A5: Add: Leave expense as per books | C5: ='4.22-4.33'!D111 -> 99574.167 | D5: ='4.22-4.33'!E111 -> 120333.33 | F5: Add: provision for leave | I5: =C5 -> 99574.167
A6: Less: Payments made | C6: ='4.11-4.17'!E95+'4.11-4.17'!E76 -> -343000 | D6: ='4.11-4.17'!F95+'4.11-4.17'!F76 -> -282000 | F6: Less: Payments | I6: =C6 -> -343000
A7: Add: Impairment of PPE | C7: ='4.22-4.33'!D164 -> 110937.29 | I7: =SUM(I3:I6) -> -2665283.8
A8: Add: Loss on sale | C8: ='4.22-4.33'!D165 -> 190501.76
A9: Add: Depreciation as per books | C9: =-SoPL!D22 -> 1366328.3
A10: Less: Depreciation as per tax | C10: -1222181.1
A11: Less: Income not taxable | C11: =-SoPL!D15 -> -359663.48
A12: Add: short term lease expense | C12: 0
A13: Add: unwinding of lease liability | C13: 0
A14: Less: Lease expense as per tax | C14: 0
A15: Add: VAT expense | C15: 0
A17: Profit as per tax | C17: =SUM(C2:C16) -> 5774990.9
A18: Provision for tax | C18: =C17*0.2 -> 1154998.2

Sheet Sheet2
